<?xml version="1.0" encoding="UTF-8" standalone="yes"?>
<p:sld xmlns:a="http://schemas.openxmlformats.org/drawingml/2006/main" xmlns:r="http://schemas.openxmlformats.org/officeDocument/2006/relationships" xmlns:p="http://schemas.openxmlformats.org/presentationml/2006/main"><p:cSld><p:spTree><p:nvGrpSpPr><p:cNvPr id="1" name=""/><p:cNvGrpSpPr/><p:nvPr/></p:nvGrpSpPr><p:grpSpPr><a:xfrm><a:off x="0" y="0"/><a:ext cx="0" cy="0"/><a:chOff x="0" y="0"/><a:chExt cx="0" cy="0"/></a:xfrm></p:grpSpPr><p:pic><p:nvPicPr><p:cNvPr id="4" name="Picture 3"/><p:cNvPicPr><a:picLocks noChangeAspect="1"/></p:cNvPicPr><p:nvPr/></p:nvPicPr><p:blipFill><a:blip r:embed="rId2"><a:extLst><a:ext uri="{28A0092B-C50C-407E-A947-70E740481C1C}"><a14:useLocalDpi xmlns:a14="http://schemas.microsoft.com/office/drawing/2010/main" val="0"/></a:ext></a:extLst></a:blip><a:stretch><a:fillRect/></a:stretch></p:blipFill><p:spPr><a:xfrm><a:off x="4655840" y="2420888"/><a:ext cx="2857500" cy="1905000"/></a:xfrm><a:prstGeom prst="rect"><a:avLst/></a:prstGeom></p:spPr></p:pic><p:pic><p:nvPicPr><p:cNvPr id="7" name="Picture 6"/><p:cNvPicPr><a:picLocks noChangeAspect="1"/></p:cNvPicPr><p:nvPr/></p:nvPicPr><p:blipFill><a:blip r:embed="rId3"><a:extLst><a:ext uri="{28A0092B-C50C-407E-A947-70E740481C1C}"><a14:useLocalDpi xmlns:a14="http://schemas.microsoft.com/office/drawing/2010/main" val="0"/></a:ext></a:extLst></a:blip><a:stretch><a:fillRect/></a:stretch></p:blipFill><p:spPr><a:xfrm><a:off x="419888" y="2424560"/><a:ext cx="1787681" cy="1524892"/></a:xfrm><a:prstGeom prst="rect"><a:avLst/></a:prstGeom></p:spPr></p:pic><p:pic><p:nvPicPr><p:cNvPr id="8" name="Picture 7"/><p:cNvPicPr><a:picLocks noChangeAspect="1"/></p:cNvPicPr><p:nvPr/></p:nvPicPr><p:blipFill><a:blip r:embed="rId4"><a:extLst><a:ext uri="{28A0092B-C50C-407E-A947-70E740481C1C}"><a14:useLocalDpi xmlns:a14="http://schemas.microsoft.com/office/drawing/2010/main" val="0"/></a:ext></a:extLst></a:blip><a:stretch><a:fillRect/></a:stretch></p:blipFill><p:spPr><a:xfrm><a:off x="2928378" y="2679513"/><a:ext cx="1014986" cy="1014986"/></a:xfrm><a:prstGeom prst="rect"><a:avLst/></a:prstGeom></p:spPr></p:pic><p:pic><p:nvPicPr><p:cNvPr id="9" name="Picture 8"/><p:cNvPicPr><a:picLocks noChangeAspect="1"/></p:cNvPicPr><p:nvPr/></p:nvPicPr><p:blipFill><a:blip r:embed="rId5"><a:extLst><a:ext uri="{28A0092B-C50C-407E-A947-70E740481C1C}"><a14:useLocalDpi xmlns:a14="http://schemas.microsoft.com/office/drawing/2010/main" val="0"/></a:ext></a:extLst></a:blip><a:stretch><a:fillRect/></a:stretch></p:blipFill><p:spPr><a:xfrm><a:off x="4658072" y="675184"/><a:ext cx="1152128" cy="1152128"/></a:xfrm><a:prstGeom prst="rect"><a:avLst/></a:prstGeom></p:spPr></p:pic><p:pic><p:nvPicPr><p:cNvPr id="10" name="Picture 9"/><p:cNvPicPr><a:picLocks noChangeAspect="1"/></p:cNvPicPr><p:nvPr/></p:nvPicPr><p:blipFill><a:blip r:embed="rId6"><a:extLst><a:ext uri="{28A0092B-C50C-407E-A947-70E740481C1C}"><a14:useLocalDpi xmlns:a14="http://schemas.microsoft.com/office/drawing/2010/main" val="0"/></a:ext></a:extLst></a:blip><a:stretch><a:fillRect/></a:stretch></p:blipFill><p:spPr><a:xfrm><a:off x="6481167" y="836712"/><a:ext cx="990600" cy="990600"/></a:xfrm><a:prstGeom prst="rect"><a:avLst/></a:prstGeom></p:spPr></p:pic><p:pic><p:nvPicPr><p:cNvPr id="11" name="Picture 10"/><p:cNvPicPr><a:picLocks noChangeAspect="1"/></p:cNvPicPr><p:nvPr/></p:nvPicPr><p:blipFill><a:blip r:embed="rId7"><a:extLst><a:ext uri="{28A0092B-C50C-407E-A947-70E740481C1C}"><a14:useLocalDpi xmlns:a14="http://schemas.microsoft.com/office/drawing/2010/main" val="0"/></a:ext></a:extLst></a:blip><a:stretch><a:fillRect/></a:stretch></p:blipFill><p:spPr><a:xfrm><a:off x="10128448" y="2659013"/><a:ext cx="1428750" cy="1453133"/></a:xfrm><a:prstGeom prst="rect"><a:avLst/></a:prstGeom></p:spPr></p:pic><p:sp><p:nvSpPr><p:cNvPr id="15" name="Oval 14"/><p:cNvSpPr/><p:nvPr/></p:nvSpPr><p:spPr><a:xfrm><a:off x="8184232" y="2703897"/><a:ext cx="1440160" cy="1408249"/></a:xfrm><a:prstGeom prst="ellipse"><a:avLst/></a:prstGeom><a:noFill/><a:ln><a:noFill/></a:ln></p:spPr><p:style><a:lnRef idx="2"><a:schemeClr val="accent1"><a:shade val="50000"/></a:schemeClr></a:lnRef><a:fillRef idx="1"><a:schemeClr val="accent1"/></a:fillRef><a:effectRef idx="0"><a:schemeClr val="accent1"/></a:effectRef><a:fontRef idx="minor"><a:schemeClr val="lt1"/></a:fontRef></p:style><p:txBody><a:bodyPr rot="0" spcFirstLastPara="0" vertOverflow="overflow" horzOverflow="overflow" vert="horz" wrap="square" lIns="91440" tIns="45720" rIns="91440" bIns="45720" numCol="1" spcCol="0" rtlCol="0" fromWordArt="0" anchor="ctr" anchorCtr="0" forceAA="0" compatLnSpc="1"><a:prstTxWarp prst="textNoShape"><a:avLst/></a:prstTxWarp><a:noAutofit/></a:bodyPr><a:lstStyle/><a:p><a:pPr algn="ctr"/><a:endParaRPr lang="ko-KR" altLang="en-US" dirty="0" err="1"><a:solidFill><a:schemeClr val="bg1"/></a:solidFill></a:endParaRPr></a:p></p:txBody></p:sp><p:pic><p:nvPicPr><p:cNvPr id="20" name="Picture 19"/><p:cNvPicPr><a:picLocks noChangeAspect="1"/></p:cNvPicPr><p:nvPr/></p:nvPicPr><p:blipFill><a:blip r:embed="rId8"><a:extLst><a:ext uri="{28A0092B-C50C-407E-A947-70E740481C1C}"><a14:useLocalDpi xmlns:a14="http://schemas.microsoft.com/office/drawing/2010/main" val="0"/></a:ext></a:extLst></a:blip><a:stretch><a:fillRect/></a:stretch></p:blipFill><p:spPr><a:xfrm><a:off x="5087888" y="4509120"/><a:ext cx="2029122" cy="1862336"/></a:xfrm><a:prstGeom prst="rect"><a:avLst/></a:prstGeom></p:spPr></p:pic><p:pic><p:nvPicPr><p:cNvPr id="21" name="Picture 20"/><p:cNvPicPr><a:picLocks noChangeAspect="1"/></p:cNvPicPr><p:nvPr/></p:nvPicPr><p:blipFill><a:blip r:embed="rId9"><a:extLst><a:ext uri="{28A0092B-C50C-407E-A947-70E740481C1C}"><a14:useLocalDpi xmlns:a14="http://schemas.microsoft.com/office/drawing/2010/main" val="0"/></a:ext></a:extLst></a:blip><a:stretch><a:fillRect/></a:stretch></p:blipFill><p:spPr><a:xfrm><a:off x="8095258" y="2659013"/><a:ext cx="1618109" cy="1618109"/></a:xfrm><a:prstGeom prst="rect"><a:avLst/></a:prstGeom></p:spPr></p:pic><p:cxnSp><p:nvCxnSpPr><p:cNvPr id="17" name="Straight Connector 16"/><p:cNvCxnSpPr/><p:nvPr/></p:nvCxnSpPr><p:spPr><a:xfrm flipH="1"><a:off x="8311722" y="2703897"/><a:ext cx="1312671" cy="1453133"/></a:xfrm><a:prstGeom prst="line"><a:avLst/></a:prstGeom><a:ln w="101600"/></p:spPr><p:style><a:lnRef idx="1"><a:schemeClr val="accent2"/></a:lnRef><a:fillRef idx="0"><a:schemeClr val="accent2"/></a:fillRef><a:effectRef idx="0"><a:schemeClr val="accent2"/></a:effectRef><a:fontRef idx="minor"><a:schemeClr val="tx1"/></a:fontRef></p:style></p:cxnSp><p:sp><p:nvSpPr><p:cNvPr id="23" name="TextBox 22"/><p:cNvSpPr txBox="1"/><p:nvPr/></p:nvSpPr><p:spPr><a:xfrm><a:off x="1559496" y="924177"/><a:ext cx="1712198" cy="646331"/></a:xfrm><a:prstGeom prst="rect"><a:avLst/></a:prstGeom><a:noFill/></p:spPr><p:txBody><a:bodyPr wrap="square" rtlCol="0"><a:spAutoFit/></a:bodyPr><a:lstStyle/><a:p><a:pPr><a:lnSpc><a:spcPct val="90000"/></a:lnSpc></a:pPr><a:r><a:rPr lang="en-US" altLang="ko-KR" sz="4000" dirty="0"><a:latin typeface="HY헤드라인M" panose="02030600000101010101" pitchFamily="18" charset="-127"/><a:ea typeface="HY헤드라인M" panose="02030600000101010101" pitchFamily="18" charset="-127"/></a:rPr><a:t>DAEGU</a:t></a:r><a:endParaRPr lang="ko-KR" altLang="en-US" sz="4000" dirty="0"><a:latin typeface="HY헤드라인M" panose="02030600000101010101" pitchFamily="18" charset="-127"/><a:ea typeface="HY헤드라인M" panose="02030600000101010101" pitchFamily="18" charset="-127"/></a:endParaRPr></a:p></p:txBody></p:sp><p:sp><p:nvSpPr><p:cNvPr id="24" name="TextBox 23"/><p:cNvSpPr txBox="1"/><p:nvPr/></p:nvSpPr><p:spPr><a:xfrm><a:off x="8957149" y="928083"/><a:ext cx="1712198" cy="646331"/></a:xfrm><a:prstGeom prst="rect"><a:avLst/></a:prstGeom><a:noFill/></p:spPr><p:txBody><a:bodyPr wrap="square" rtlCol="0"><a:spAutoFit/></a:bodyPr><a:lstStyle/><a:p><a:pPr><a:lnSpc><a:spcPct val="90000"/></a:lnSpc></a:pPr><a:r><a:rPr lang="en-US" altLang="ko-KR" sz="4000" dirty="0"><a:latin typeface="HY헤드라인M" panose="02030600000101010101" pitchFamily="18" charset="-127"/><a:ea typeface="HY헤드라인M" panose="02030600000101010101" pitchFamily="18" charset="-127"/></a:rPr><a:t>DAEGU</a:t></a:r><a:endParaRPr lang="ko-KR" altLang="en-US" sz="4000" dirty="0"><a:latin typeface="HY헤드라인M" panose="02030600000101010101" pitchFamily="18" charset="-127"/><a:ea typeface="HY헤드라인M" panose="02030600000101010101" pitchFamily="18" charset="-127"/></a:endParaRPr></a:p></p:txBody></p:sp><p:sp><p:nvSpPr><p:cNvPr id="25" name="TextBox 24"/><p:cNvSpPr txBox="1"/><p:nvPr/></p:nvSpPr><p:spPr><a:xfrm><a:off x="9200728" y="5269523"/><a:ext cx="1712198" cy="646331"/></a:xfrm><a:prstGeom prst="rect"><a:avLst/></a:prstGeom><a:noFill/></p:spPr><p:txBody><a:bodyPr wrap="square" rtlCol="0"><a:spAutoFit/></a:bodyPr><a:lstStyle/><a:p><a:pPr><a:lnSpc><a:spcPct val="90000"/></a:lnSpc></a:pPr><a:r><a:rPr lang="en-US" altLang="ko-KR" sz="4000" dirty="0"><a:latin typeface="HY헤드라인M" panose="02030600000101010101" pitchFamily="18" charset="-127"/><a:ea typeface="HY헤드라인M" panose="02030600000101010101" pitchFamily="18" charset="-127"/></a:rPr><a:t>DAEGU</a:t></a:r><a:endParaRPr lang="ko-KR" altLang="en-US" sz="4000" dirty="0"><a:latin typeface="HY헤드라인M" panose="02030600000101010101" pitchFamily="18" charset="-127"/><a:ea typeface="HY헤드라인M" panose="02030600000101010101" pitchFamily="18" charset="-127"/></a:endParaRPr></a:p></p:txBody></p:sp><p:sp><p:nvSpPr><p:cNvPr id="26" name="TextBox 25"/><p:cNvSpPr txBox="1"/><p:nvPr/></p:nvSpPr><p:spPr><a:xfrm><a:off x="1559496" y="5269522"/><a:ext cx="1712198" cy="646331"/></a:xfrm><a:prstGeom prst="rect"><a:avLst/></a:prstGeom><a:noFill/></p:spPr><p:txBody><a:bodyPr wrap="square" rtlCol="0"><a:spAutoFit/></a:bodyPr><a:lstStyle/><a:p><a:pPr><a:lnSpc><a:spcPct val="90000"/></a:lnSpc></a:pPr><a:r><a:rPr lang="en-US" altLang="ko-KR" sz="4000" dirty="0"><a:latin typeface="HY헤드라인M" panose="02030600000101010101" pitchFamily="18" charset="-127"/><a:ea typeface="HY헤드라인M" panose="02030600000101010101" pitchFamily="18" charset="-127"/></a:rPr><a:t>DAEGU</a:t></a:r><a:endParaRPr lang="ko-KR" altLang="en-US" sz="4000" dirty="0"><a:latin typeface="HY헤드라인M" panose="02030600000101010101" pitchFamily="18" charset="-127"/><a:ea typeface="HY헤드라인M" panose="02030600000101010101" pitchFamily="18" charset="-127"/></a:endParaRPr></a:p></p:txBody></p:sp></p:spTree><p:extLst><p:ext uri="{BB962C8B-B14F-4D97-AF65-F5344CB8AC3E}"><p14:creationId xmlns:p14="http://schemas.microsoft.com/office/powerpoint/2010/main" val="2347082623"/></p:ext></p:extLst></p:cSld><p:clrMapOvr><a:masterClrMapping/></p:clrMapOvr><mc:AlternateContent xmlns:mc="http://schemas.openxmlformats.org/markup-compatibility/2006" xmlns:p14="http://schemas.microsoft.com/office/powerpoint/2010/main"><mc:Choice Requires="p14"><p:transition spd="med" p14:dur="700"><p:fade/></p:transition></mc:Choice><mc:Fallback xmlns="">
      <p:transition spd="med">
        <p:fade/>
      </p:transition>
    </mc:Fallback></mc:AlternateContent><p:timing><p:tnLst><p:par><p:cTn id="1" dur="indefinite" restart="never" nodeType="tmRoot"><p:childTnLst><p:seq concurrent="1" nextAc="seek"><p:cTn id="2" dur="indefinite" nodeType="mainSeq"><p:childTnLst><p:par><p:cTn id="3" fill="hold"><p:stCondLst><p:cond delay="indefinite"/></p:stCondLst><p:childTnLst><p:par><p:cTn id="4" fill="hold"><p:stCondLst><p:cond delay="0"/></p:stCondLst><p:childTnLst><p:par><p:cTn id="5" presetID="10" presetClass="entr" presetSubtype="0" fill="hold" nodeType="clickEffect"><p:stCondLst><p:cond delay="0"/></p:stCondLst><p:childTnLst><p:set><p:cBhvr><p:cTn id="6" dur="1" fill="hold"><p:stCondLst><p:cond delay="0"/></p:stCondLst></p:cTn><p:tgtEl><p:spTgt spid="7"/></p:tgtEl><p:attrNameLst><p:attrName>style.visibility</p:attrName></p:attrNameLst></p:cBhvr><p:to><p:strVal val="visible"/></p:to></p:set><p:animEffect transition="in" filter="fade"><p:cBhvr><p:cTn id="7" dur="500"/><p:tgtEl><p:spTgt spid="7"/></p:tgtEl></p:cBhvr></p:animEffect></p:childTnLst></p:cTn></p:par></p:childTnLst></p:cTn></p:par></p:childTnLst></p:cTn></p:par><p:par><p:cTn id="8" fill="hold"><p:stCondLst><p:cond delay="indefinite"/></p:stCondLst><p:childTnLst><p:par><p:cTn id="9" fill="hold"><p:stCondLst><p:cond delay="0"/></p:stCondLst><p:childTnLst><p:par><p:cTn id="10" presetID="42" presetClass="entr" presetSubtype="0" fill="hold" nodeType="clickEffect"><p:stCondLst><p:cond delay="0"/></p:stCondLst><p:childTnLst><p:set><p:cBhvr><p:cTn id="11" dur="1" fill="hold"><p:stCondLst><p:cond delay="0"/></p:stCondLst></p:cTn><p:tgtEl><p:spTgt spid="8"/></p:tgtEl><p:attrNameLst><p:attrName>style.visibility</p:attrName></p:attrNameLst></p:cBhvr><p:to><p:strVal val="visible"/></p:to></p:set><p:animEffect transition="in" filter="fade"><p:cBhvr><p:cTn id="12" dur="1000"/><p:tgtEl><p:spTgt spid="8"/></p:tgtEl></p:cBhvr></p:animEffect><p:anim calcmode="lin" valueType="num"><p:cBhvr><p:cTn id="13" dur="1000" fill="hold"/><p:tgtEl><p:spTgt spid="8"/></p:tgtEl><p:attrNameLst><p:attrName>ppt_x</p:attrName></p:attrNameLst></p:cBhvr><p:tavLst><p:tav tm="0"><p:val><p:strVal val="#ppt_x"/></p:val></p:tav><p:tav tm="100000"><p:val><p:strVal val="#ppt_x"/></p:val></p:tav></p:tavLst></p:anim><p:anim calcmode="lin" valueType="num"><p:cBhvr><p:cTn id="14" dur="1000" fill="hold"/><p:tgtEl><p:spTgt spid="8"/></p:tgtEl><p:attrNameLst><p:attrName>ppt_y</p:attrName></p:attrNameLst></p:cBhvr><p:tavLst><p:tav tm="0"><p:val><p:strVal val="#ppt_y+.1"/></p:val></p:tav><p:tav tm="100000"><p:val><p:strVal val="#ppt_y"/></p:val></p:tav></p:tavLst></p:anim></p:childTnLst></p:cTn></p:par></p:childTnLst></p:cTn></p:par></p:childTnLst></p:cTn></p:par><p:par><p:cTn id="15" fill="hold"><p:stCondLst><p:cond delay="indefinite"/></p:stCondLst><p:childTnLst><p:par><p:cTn id="16" fill="hold"><p:stCondLst><p:cond delay="0"/></p:stCondLst><p:childTnLst><p:par><p:cTn id="17" presetID="10" presetClass="entr" presetSubtype="0" fill="hold" nodeType="clickEffect"><p:stCondLst><p:cond delay="0"/></p:stCondLst><p:childTnLst><p:set><p:cBhvr><p:cTn id="18" dur="1" fill="hold"><p:stCondLst><p:cond delay="0"/></p:stCondLst></p:cTn><p:tgtEl><p:spTgt spid="9"/></p:tgtEl><p:attrNameLst><p:attrName>style.visibility</p:attrName></p:attrNameLst></p:cBhvr><p:to><p:strVal val="visible"/></p:to></p:set><p:animEffect transition="in" filter="fade"><p:cBhvr><p:cTn id="19" dur="500"/><p:tgtEl><p:spTgt spid="9"/></p:tgtEl></p:cBhvr></p:animEffect></p:childTnLst></p:cTn></p:par></p:childTnLst></p:cTn></p:par></p:childTnLst></p:cTn></p:par><p:par><p:cTn id="20" fill="hold"><p:stCondLst><p:cond delay="indefinite"/></p:stCondLst><p:childTnLst><p:par><p:cTn id="21" fill="hold"><p:stCondLst><p:cond delay="0"/></p:stCondLst><p:childTnLst><p:par><p:cTn id="22" presetID="10" presetClass="entr" presetSubtype="0" fill="hold" nodeType="clickEffect"><p:stCondLst><p:cond delay="0"/></p:stCondLst><p:childTnLst><p:set><p:cBhvr><p:cTn id="23" dur="1" fill="hold"><p:stCondLst><p:cond delay="0"/></p:stCondLst></p:cTn><p:tgtEl><p:spTgt spid="10"/></p:tgtEl><p:attrNameLst><p:attrName>style.visibility</p:attrName></p:attrNameLst></p:cBhvr><p:to><p:strVal val="visible"/></p:to></p:set><p:animEffect transition="in" filter="fade"><p:cBhvr><p:cTn id="24" dur="500"/><p:tgtEl><p:spTgt spid="10"/></p:tgtEl></p:cBhvr></p:animEffect></p:childTnLst></p:cTn></p:par></p:childTnLst></p:cTn></p:par></p:childTnLst></p:cTn></p:par><p:par><p:cTn id="25" fill="hold"><p:stCondLst><p:cond delay="indefinite"/></p:stCondLst><p:childTnLst><p:par><p:cTn id="26" fill="hold"><p:stCondLst><p:cond delay="0"/></p:stCondLst><p:childTnLst><p:par><p:cTn id="27" presetID="10" presetClass="entr" presetSubtype="0" fill="hold" nodeType="clickEffect"><p:stCondLst><p:cond delay="0"/></p:stCondLst><p:childTnLst><p:set><p:cBhvr><p:cTn id="28" dur="1" fill="hold"><p:stCondLst><p:cond delay="0"/></p:stCondLst></p:cTn><p:tgtEl><p:spTgt spid="21"/></p:tgtEl><p:attrNameLst><p:attrName>style.visibility</p:attrName></p:attrNameLst></p:cBhvr><p:to><p:strVal val="visible"/></p:to></p:set><p:animEffect transition="in" filter="fade"><p:cBhvr><p:cTn id="29" dur="500"/><p:tgtEl><p:spTgt spid="21"/></p:tgtEl></p:cBhvr></p:animEffect></p:childTnLst></p:cTn></p:par></p:childTnLst></p:cTn></p:par></p:childTnLst></p:cTn></p:par><p:par><p:cTn id="30" fill="hold"><p:stCondLst><p:cond delay="indefinite"/></p:stCondLst><p:childTnLst><p:par><p:cTn id="31" fill="hold"><p:stCondLst><p:cond delay="0"/></p:stCondLst><p:childTnLst><p:par><p:cTn id="32" presetID="10" presetClass="entr" presetSubtype="0" fill="hold" nodeType="clickEffect"><p:stCondLst><p:cond delay="0"/></p:stCondLst><p:childTnLst><p:set><p:cBhvr><p:cTn id="33" dur="1" fill="hold"><p:stCondLst><p:cond delay="0"/></p:stCondLst></p:cTn><p:tgtEl><p:spTgt spid="17"/></p:tgtEl><p:attrNameLst><p:attrName>style.visibility</p:attrName></p:attrNameLst></p:cBhvr><p:to><p:strVal val="visible"/></p:to></p:set><p:animEffect transition="in" filter="fade"><p:cBhvr><p:cTn id="34" dur="500"/><p:tgtEl><p:spTgt spid="17"/></p:tgtEl></p:cBhvr></p:animEffect></p:childTnLst></p:cTn></p:par></p:childTnLst></p:cTn></p:par></p:childTnLst></p:cTn></p:par><p:par><p:cTn id="35" fill="hold"><p:stCondLst><p:cond delay="indefinite"/></p:stCondLst><p:childTnLst><p:par><p:cTn id="36" fill="hold"><p:stCondLst><p:cond delay="0"/></p:stCondLst><p:childTnLst><p:par><p:cTn id="37" presetID="10" presetClass="entr" presetSubtype="0" fill="hold" nodeType="clickEffect"><p:stCondLst><p:cond delay="0"/></p:stCondLst><p:childTnLst><p:set><p:cBhvr><p:cTn id="38" dur="1" fill="hold"><p:stCondLst><p:cond delay="0"/></p:stCondLst></p:cTn><p:tgtEl><p:spTgt spid="11"/></p:tgtEl><p:attrNameLst><p:attrName>style.visibility</p:attrName></p:attrNameLst></p:cBhvr><p:to><p:strVal val="visible"/></p:to></p:set><p:animEffect transition="in" filter="fade"><p:cBhvr><p:cTn id="39" dur="500"/><p:tgtEl><p:spTgt spid="11"/></p:tgtEl></p:cBhvr></p:animEffect></p:childTnLst></p:cTn></p:par></p:childTnLst></p:cTn></p:par></p:childTnLst></p:cTn></p:par><p:par><p:cTn id="40" fill="hold"><p:stCondLst><p:cond delay="indefinite"/></p:stCondLst><p:childTnLst><p:par><p:cTn id="41" fill="hold"><p:stCondLst><p:cond delay="0"/></p:stCondLst><p:childTnLst><p:par><p:cTn id="42" presetID="10" presetClass="entr" presetSubtype="0" fill="hold" nodeType="clickEffect"><p:stCondLst><p:cond delay="0"/></p:stCondLst><p:childTnLst><p:set><p:cBhvr><p:cTn id="43" dur="1" fill="hold"><p:stCondLst><p:cond delay="0"/></p:stCondLst></p:cTn><p:tgtEl><p:spTgt spid="20"/></p:tgtEl><p:attrNameLst><p:attrName>style.visibility</p:attrName></p:attrNameLst></p:cBhvr><p:to><p:strVal val="visible"/></p:to></p:set><p:animEffect transition="in" filter="fade"><p:cBhvr><p:cTn id="44" dur="500"/><p:tgtEl><p:spTgt spid="20"/></p:tgtEl></p:cBhvr></p:animEffect></p:childTnLst></p:cTn></p:par></p:childTnLst></p:cTn></p:par></p:childTnLst></p:cTn></p:par><p:par><p:cTn id="45" fill="hold"><p:stCondLst><p:cond delay="indefinite"/></p:stCondLst><p:childTnLst><p:par><p:cTn id="46" fill="hold"><p:stCondLst><p:cond delay="0"/></p:stCondLst><p:childTnLst><p:par><p:cTn id="47" presetID="31" presetClass="entr" presetSubtype="0" fill="hold" grpId="0" nodeType="clickEffect"><p:stCondLst><p:cond delay="0"/></p:stCondLst><p:childTnLst><p:set><p:cBhvr><p:cTn id="48" dur="1" fill="hold"><p:stCondLst><p:cond delay="0"/></p:stCondLst></p:cTn><p:tgtEl><p:spTgt spid="23"/></p:tgtEl><p:attrNameLst><p:attrName>style.visibility</p:attrName></p:attrNameLst></p:cBhvr><p:to><p:strVal val="visible"/></p:to></p:set><p:anim calcmode="lin" valueType="num"><p:cBhvr><p:cTn id="49" dur="1000" fill="hold"/><p:tgtEl><p:spTgt spid="23"/></p:tgtEl><p:attrNameLst><p:attrName>ppt_w</p:attrName></p:attrNameLst></p:cBhvr><p:tavLst><p:tav tm="0"><p:val><p:fltVal val="0"/></p:val></p:tav><p:tav tm="100000"><p:val><p:strVal val="#ppt_w"/></p:val></p:tav></p:tavLst></p:anim><p:anim calcmode="lin" valueType="num"><p:cBhvr><p:cTn id="50" dur="1000" fill="hold"/><p:tgtEl><p:spTgt spid="23"/></p:tgtEl><p:attrNameLst><p:attrName>ppt_h</p:attrName></p:attrNameLst></p:cBhvr><p:tavLst><p:tav tm="0"><p:val><p:fltVal val="0"/></p:val></p:tav><p:tav tm="100000"><p:val><p:strVal val="#ppt_h"/></p:val></p:tav></p:tavLst></p:anim><p:anim calcmode="lin" valueType="num"><p:cBhvr><p:cTn id="51" dur="1000" fill="hold"/><p:tgtEl><p:spTgt spid="23"/></p:tgtEl><p:attrNameLst><p:attrName>style.rotation</p:attrName></p:attrNameLst></p:cBhvr><p:tavLst><p:tav tm="0"><p:val><p:fltVal val="90"/></p:val></p:tav><p:tav tm="100000"><p:val><p:fltVal val="0"/></p:val></p:tav></p:tavLst></p:anim><p:animEffect transition="in" filter="fade"><p:cBhvr><p:cTn id="52" dur="1000"/><p:tgtEl><p:spTgt spid="23"/></p:tgtEl></p:cBhvr></p:animEffect></p:childTnLst></p:cTn></p:par><p:par><p:cTn id="53" presetID="31" presetClass="entr" presetSubtype="0" fill="hold" grpId="0" nodeType="withEffect"><p:stCondLst><p:cond delay="0"/></p:stCondLst><p:childTnLst><p:set><p:cBhvr><p:cTn id="54" dur="1" fill="hold"><p:stCondLst><p:cond delay="0"/></p:stCondLst></p:cTn><p:tgtEl><p:spTgt spid="24"/></p:tgtEl><p:attrNameLst><p:attrName>style.visibility</p:attrName></p:attrNameLst></p:cBhvr><p:to><p:strVal val="visible"/></p:to></p:set><p:anim calcmode="lin" valueType="num"><p:cBhvr><p:cTn id="55" dur="1000" fill="hold"/><p:tgtEl><p:spTgt spid="24"/></p:tgtEl><p:attrNameLst><p:attrName>ppt_w</p:attrName></p:attrNameLst></p:cBhvr><p:tavLst><p:tav tm="0"><p:val><p:fltVal val="0"/></p:val></p:tav><p:tav tm="100000"><p:val><p:strVal val="#ppt_w"/></p:val></p:tav></p:tavLst></p:anim><p:anim calcmode="lin" valueType="num"><p:cBhvr><p:cTn id="56" dur="1000" fill="hold"/><p:tgtEl><p:spTgt spid="24"/></p:tgtEl><p:attrNameLst><p:attrName>ppt_h</p:attrName></p:attrNameLst></p:cBhvr><p:tavLst><p:tav tm="0"><p:val><p:fltVal val="0"/></p:val></p:tav><p:tav tm="100000"><p:val><p:strVal val="#ppt_h"/></p:val></p:tav></p:tavLst></p:anim><p:anim calcmode="lin" valueType="num"><p:cBhvr><p:cTn id="57" dur="1000" fill="hold"/><p:tgtEl><p:spTgt spid="24"/></p:tgtEl><p:attrNameLst><p:attrName>style.rotation</p:attrName></p:attrNameLst></p:cBhvr><p:tavLst><p:tav tm="0"><p:val><p:fltVal val="90"/></p:val></p:tav><p:tav tm="100000"><p:val><p:fltVal val="0"/></p:val></p:tav></p:tavLst></p:anim><p:animEffect transition="in" filter="fade"><p:cBhvr><p:cTn id="58" dur="1000"/><p:tgtEl><p:spTgt spid="24"/></p:tgtEl></p:cBhvr></p:animEffect></p:childTnLst></p:cTn></p:par><p:par><p:cTn id="59" presetID="31" presetClass="entr" presetSubtype="0" fill="hold" grpId="0" nodeType="withEffect"><p:stCondLst><p:cond delay="0"/></p:stCondLst><p:childTnLst><p:set><p:cBhvr><p:cTn id="60" dur="1" fill="hold"><p:stCondLst><p:cond delay="0"/></p:stCondLst></p:cTn><p:tgtEl><p:spTgt spid="25"/></p:tgtEl><p:attrNameLst><p:attrName>style.visibility</p:attrName></p:attrNameLst></p:cBhvr><p:to><p:strVal val="visible"/></p:to></p:set><p:anim calcmode="lin" valueType="num"><p:cBhvr><p:cTn id="61" dur="1000" fill="hold"/><p:tgtEl><p:spTgt spid="25"/></p:tgtEl><p:attrNameLst><p:attrName>ppt_w</p:attrName></p:attrNameLst></p:cBhvr><p:tavLst><p:tav tm="0"><p:val><p:fltVal val="0"/></p:val></p:tav><p:tav tm="100000"><p:val><p:strVal val="#ppt_w"/></p:val></p:tav></p:tavLst></p:anim><p:anim calcmode="lin" valueType="num"><p:cBhvr><p:cTn id="62" dur="1000" fill="hold"/><p:tgtEl><p:spTgt spid="25"/></p:tgtEl><p:attrNameLst><p:attrName>ppt_h</p:attrName></p:attrNameLst></p:cBhvr><p:tavLst><p:tav tm="0"><p:val><p:fltVal val="0"/></p:val></p:tav><p:tav tm="100000"><p:val><p:strVal val="#ppt_h"/></p:val></p:tav></p:tavLst></p:anim><p:anim calcmode="lin" valueType="num"><p:cBhvr><p:cTn id="63" dur="1000" fill="hold"/><p:tgtEl><p:spTgt spid="25"/></p:tgtEl><p:attrNameLst><p:attrName>style.rotation</p:attrName></p:attrNameLst></p:cBhvr><p:tavLst><p:tav tm="0"><p:val><p:fltVal val="90"/></p:val></p:tav><p:tav tm="100000"><p:val><p:fltVal val="0"/></p:val></p:tav></p:tavLst></p:anim><p:animEffect transition="in" filter="fade"><p:cBhvr><p:cTn id="64" dur="1000"/><p:tgtEl><p:spTgt spid="25"/></p:tgtEl></p:cBhvr></p:animEffect></p:childTnLst></p:cTn></p:par><p:par><p:cTn id="65" presetID="31" presetClass="entr" presetSubtype="0" fill="hold" grpId="0" nodeType="withEffect"><p:stCondLst><p:cond delay="0"/></p:stCondLst><p:childTnLst><p:set><p:cBhvr><p:cTn id="66" dur="1" fill="hold"><p:stCondLst><p:cond delay="0"/></p:stCondLst></p:cTn><p:tgtEl><p:spTgt spid="26"/></p:tgtEl><p:attrNameLst><p:attrName>style.visibility</p:attrName></p:attrNameLst></p:cBhvr><p:to><p:strVal val="visible"/></p:to></p:set><p:anim calcmode="lin" valueType="num"><p:cBhvr><p:cTn id="67" dur="1000" fill="hold"/><p:tgtEl><p:spTgt spid="26"/></p:tgtEl><p:attrNameLst><p:attrName>ppt_w</p:attrName></p:attrNameLst></p:cBhvr><p:tavLst><p:tav tm="0"><p:val><p:fltVal val="0"/></p:val></p:tav><p:tav tm="100000"><p:val><p:strVal val="#ppt_w"/></p:val></p:tav></p:tavLst></p:anim><p:anim calcmode="lin" valueType="num"><p:cBhvr><p:cTn id="68" dur="1000" fill="hold"/><p:tgtEl><p:spTgt spid="26"/></p:tgtEl><p:attrNameLst><p:attrName>ppt_h</p:attrName></p:attrNameLst></p:cBhvr><p:tavLst><p:tav tm="0"><p:val><p:fltVal val="0"/></p:val></p:tav><p:tav tm="100000"><p:val><p:strVal val="#ppt_h"/></p:val></p:tav></p:tavLst></p:anim><p:anim calcmode="lin" valueType="num"><p:cBhvr><p:cTn id="69" dur="1000" fill="hold"/><p:tgtEl><p:spTgt spid="26"/></p:tgtEl><p:attrNameLst><p:attrName>style.rotation</p:attrName></p:attrNameLst></p:cBhvr><p:tavLst><p:tav tm="0"><p:val><p:fltVal val="90"/></p:val></p:tav><p:tav tm="100000"><p:val><p:fltVal val="0"/></p:val></p:tav></p:tavLst></p:anim><p:animEffect transition="in" filter="fade"><p:cBhvr><p:cTn id="70" dur="1000"/><p:tgtEl><p:spTgt spid="26"/></p:tgtEl></p:cBhvr></p:animEffect></p:childTnLst></p:cTn></p:par></p:childTnLst></p:cTn></p:par></p:childTnLst></p:cTn></p:par></p:childTnLst></p:cTn><p:prevCondLst><p:cond evt="onPrev" delay="0"><p:tgtEl><p:sldTgt/></p:tgtEl></p:cond></p:prevCondLst><p:nextCondLst><p:cond evt="onNext" delay="0"><p:tgtEl><p:sldTgt/></p:tgtEl></p:cond></p:nextCondLst></p:seq></p:childTnLst></p:cTn></p:par></p:tnLst><p:bldLst><p:bldP spid="23" grpId="0"/><p:bldP spid="24" grpId="0"/><p:bldP spid="25" grpId="0"/><p:bldP spid="26" grpId="0"/></p:bldLst></p:timing></p:sld>