<?xml version="1.0" encoding="UTF-8" standalone="yes"?>
<p:sld xmlns:a="http://schemas.openxmlformats.org/drawingml/2006/main" xmlns:r="http://schemas.openxmlformats.org/officeDocument/2006/relationships" xmlns:p="http://schemas.openxmlformats.org/presentationml/2006/main"><p:cSld><p:spTree><p:nvGrpSpPr><p:cNvPr id="1" name=""/><p:cNvGrpSpPr/><p:nvPr/></p:nvGrpSpPr><p:grpSpPr><a:xfrm><a:off x="0" y="0"/><a:ext cx="0" cy="0"/><a:chOff x="0" y="0"/><a:chExt cx="0" cy="0"/></a:xfrm></p:grpSpPr><p:sp><p:nvSpPr><p:cNvPr id="10240" name="직사각형 10239"/><p:cNvSpPr/><p:nvPr/></p:nvSpPr><p:spPr><a:xfrm><a:off x="3065557" y="1932960"/><a:ext cx="2646706" cy="45719"/></a:xfrm><a:prstGeom prst="rect"><a:avLst/></a:prstGeom><a:solidFill><a:srgbClr val="FFFF00"/></a:solidFill><a:ln><a:noFill/></a:ln></p:spPr><p:style><a:lnRef idx="2"><a:schemeClr val="accent1"><a:shade val="50000"/></a:schemeClr></a:lnRef><a:fillRef idx="1"><a:schemeClr val="accent1"/></a:fillRef><a:effectRef idx="0"><a:schemeClr val="accent1"/></a:effectRef><a:fontRef idx="minor"><a:schemeClr val="lt1"/></a:fontRef></p:style><p:txBody><a:bodyPr rtlCol="0" anchor="ctr"/><a:lstStyle/><a:p><a:pPr algn="ctr"/><a:endParaRPr lang="ko-KR" altLang="en-US"/></a:p></p:txBody></p:sp><p:sp><p:nvSpPr><p:cNvPr id="51" name="TextBox 50"/><p:cNvSpPr txBox="1"/><p:nvPr/></p:nvSpPr><p:spPr><a:xfrm><a:off x="4539033" y="2666213"/><a:ext cx="184731" cy="338554"/></a:xfrm><a:prstGeom prst="rect"><a:avLst/></a:prstGeom><a:noFill/></p:spPr><p:txBody><a:bodyPr wrap="none" rtlCol="0"><a:spAutoFit/></a:bodyPr><a:lstStyle/><a:p><a:pPr algn="ctr"/><a:endParaRPr lang="ko-KR" altLang="en-US" sz="1600" dirty="0"><a:ln><a:solidFill><a:srgbClr val="4F81BD"><a:shade val="50000"/><a:alpha val="0"/></a:srgbClr></a:solidFill></a:ln><a:solidFill><a:prstClr val="black"/></a:solidFill><a:latin typeface="KoPub돋움체 Bold" pitchFamily="18" charset="-127"/><a:ea typeface="KoPub돋움체 Bold" pitchFamily="18" charset="-127"/></a:endParaRPr></a:p></p:txBody></p:sp><p:sp><p:nvSpPr><p:cNvPr id="52" name="TextBox 51"/><p:cNvSpPr txBox="1"/><p:nvPr/></p:nvSpPr><p:spPr><a:xfrm><a:off x="6003596" y="3443463"/><a:ext cx="184731" cy="338554"/></a:xfrm><a:prstGeom prst="rect"><a:avLst/></a:prstGeom><a:noFill/></p:spPr><p:txBody><a:bodyPr wrap="none" rtlCol="0"><a:spAutoFit/></a:bodyPr><a:lstStyle/><a:p><a:pPr algn="ctr"/><a:endParaRPr lang="ko-KR" altLang="en-US" sz="1600" dirty="0"><a:ln><a:solidFill><a:srgbClr val="4F81BD"><a:shade val="50000"/><a:alpha val="0"/></a:srgbClr></a:solidFill></a:ln><a:solidFill><a:prstClr val="black"/></a:solidFill><a:latin typeface="KoPub돋움체 Bold" pitchFamily="18" charset="-127"/><a:ea typeface="KoPub돋움체 Bold" pitchFamily="18" charset="-127"/></a:endParaRPr></a:p></p:txBody></p:sp><p:sp><p:nvSpPr><p:cNvPr id="55" name="TextBox 54"/><p:cNvSpPr txBox="1"/><p:nvPr/></p:nvSpPr><p:spPr><a:xfrm><a:off x="7458693" y="3543386"/><a:ext cx="184731" cy="338554"/></a:xfrm><a:prstGeom prst="rect"><a:avLst/></a:prstGeom><a:noFill/></p:spPr><p:txBody><a:bodyPr wrap="none" rtlCol="0"><a:spAutoFit/></a:bodyPr><a:lstStyle/><a:p><a:pPr algn="ctr"/><a:endParaRPr lang="ko-KR" altLang="en-US" sz="1600" dirty="0"><a:ln><a:solidFill><a:srgbClr val="4F81BD"><a:shade val="50000"/><a:alpha val="0"/></a:srgbClr></a:solidFill></a:ln><a:solidFill><a:prstClr val="black"/></a:solidFill><a:latin typeface="KoPub돋움체 Bold" pitchFamily="18" charset="-127"/><a:ea typeface="KoPub돋움체 Bold" pitchFamily="18" charset="-127"/></a:endParaRPr></a:p></p:txBody></p:sp><p:pic><p:nvPicPr><p:cNvPr id="10243" name="그림 10242"/><p:cNvPicPr><a:picLocks noChangeAspect="1"/></p:cNvPicPr><p:nvPr/></p:nvPicPr><p:blipFill><a:blip r:embed="rId3" cstate="print"><a:extLst><a:ext uri="{BEBA8EAE-BF5A-486C-A8C5-ECC9F3942E4B}"><a14:imgProps xmlns:a14="http://schemas.microsoft.com/office/drawing/2010/main"><a14:imgLayer r:embed="rId4"><a14:imgEffect><a14:backgroundRemoval t="6538" b="92538" l="10000" r="90000"><a14:foregroundMark x1="32923" y1="12077" x2="32923" y2="12077"/><a14:foregroundMark x1="36231" y1="15385" x2="36231" y2="15385"/><a14:foregroundMark x1="31077" y1="15538" x2="31077" y2="15538"/><a14:foregroundMark x1="36231" y1="21000" x2="36231" y2="21000"/></a14:backgroundRemoval></a14:imgEffect></a14:imgLayer></a14:imgProps></a:ext><a:ext uri="{28A0092B-C50C-407E-A947-70E740481C1C}"><a14:useLocalDpi xmlns:a14="http://schemas.microsoft.com/office/drawing/2010/main" val="0"/></a:ext></a:extLst></a:blip><a:stretch><a:fillRect/></a:stretch></p:blipFill><p:spPr><a:xfrm><a:off x="1970982" y="1052736"/><a:ext cx="1244698" cy="1244698"/></a:xfrm><a:prstGeom prst="rect"><a:avLst/></a:prstGeom></p:spPr></p:pic><p:grpSp><p:nvGrpSpPr><p:cNvPr id="3" name="그룹 73"/><p:cNvGrpSpPr/><p:nvPr/></p:nvGrpSpPr><p:grpSpPr><a:xfrm><a:off x="1337451" y="-171400"/><a:ext cx="9505056" cy="7056784"/><a:chOff x="-186549" y="-171400"/><a:chExt cx="9505056" cy="7056784"/></a:xfrm></p:grpSpPr><p:sp><p:nvSpPr><p:cNvPr id="77" name="모서리가 둥근 직사각형 76"/><p:cNvSpPr/><p:nvPr/></p:nvSpPr><p:spPr><a:xfrm><a:off x="8983986" y="404664"/><a:ext cx="153993" cy="6480720"/></a:xfrm><a:prstGeom prst="roundRect"><a:avLst/></a:prstGeom><a:solidFill><a:srgbClr val="ECEDEE"/></a:solidFill><a:ln><a:noFill/></a:ln></p:spPr><p:style><a:lnRef idx="2"><a:schemeClr val="accent1"><a:shade val="50000"/></a:schemeClr></a:lnRef><a:fillRef idx="1"><a:schemeClr val="accent1"/></a:fillRef><a:effectRef idx="0"><a:schemeClr val="accent1"/></a:effectRef><a:fontRef idx="minor"><a:schemeClr val="lt1"/></a:fontRef></p:style><p:txBody><a:bodyPr rtlCol="0" anchor="ctr"/><a:lstStyle/><a:p><a:pPr algn="ctr"/><a:endParaRPr lang="ko-KR" altLang="en-US" dirty="0"/></a:p></p:txBody></p:sp><p:sp><p:nvSpPr><p:cNvPr id="78" name="직사각형 77"/><p:cNvSpPr/><p:nvPr/></p:nvSpPr><p:spPr><a:xfrm><a:off x="-186549" y="-171400"/><a:ext cx="9505056" cy="576064"/></a:xfrm><a:prstGeom prst="rect"><a:avLst/></a:prstGeom><a:solidFill><a:schemeClr val="accent3"><a:lumMod val="75000"/></a:schemeClr></a:solidFill><a:ln><a:noFill/></a:ln></p:spPr><p:style><a:lnRef idx="2"><a:schemeClr val="accent1"><a:shade val="50000"/></a:schemeClr></a:lnRef><a:fillRef idx="1"><a:schemeClr val="accent1"/></a:fillRef><a:effectRef idx="0"><a:schemeClr val="accent1"/></a:effectRef><a:fontRef idx="minor"><a:schemeClr val="lt1"/></a:fontRef></p:style><p:txBody><a:bodyPr rtlCol="0" anchor="ctr"/><a:lstStyle/><a:p><a:pPr algn="ctr"/><a:endParaRPr lang="ko-KR" altLang="en-US"/></a:p></p:txBody></p:sp><p:sp><p:nvSpPr><p:cNvPr id="79" name="모서리가 둥근 직사각형 78"/><p:cNvSpPr/><p:nvPr/></p:nvSpPr><p:spPr><a:xfrm><a:off x="6219499" y="87613"/><a:ext cx="2018888" cy="226445"/></a:xfrm><a:prstGeom prst="roundRect"><a:avLst><a:gd name="adj" fmla="val 27183"/></a:avLst></a:prstGeom><a:solidFill><a:schemeClr val="bg1"/></a:solidFill><a:ln><a:solidFill><a:srgbClr val="BEB7BD"/></a:solidFill></a:ln></p:spPr><p:style><a:lnRef idx="2"><a:schemeClr val="accent1"><a:shade val="50000"/></a:schemeClr></a:lnRef><a:fillRef idx="1"><a:schemeClr val="accent1"/></a:fillRef><a:effectRef idx="0"><a:schemeClr val="accent1"/></a:effectRef><a:fontRef idx="minor"><a:schemeClr val="lt1"/></a:fontRef></p:style><p:txBody><a:bodyPr rtlCol="0" anchor="ctr"/><a:lstStyle/><a:p><a:pPr algn="ctr"/><a:endParaRPr lang="ko-KR" altLang="en-US"/></a:p></p:txBody></p:sp><p:sp><p:nvSpPr><p:cNvPr id="80" name="모서리가 둥근 직사각형 79"/><p:cNvSpPr/><p:nvPr/></p:nvSpPr><p:spPr><a:xfrm><a:off x="1685659" y="102853"/><a:ext cx="4176464" cy="226445"/></a:xfrm><a:prstGeom prst="roundRect"><a:avLst><a:gd name="adj" fmla="val 27183"/></a:avLst></a:prstGeom><a:solidFill><a:schemeClr val="bg1"/></a:solidFill><a:ln><a:solidFill><a:srgbClr val="BEB7BD"/></a:solidFill></a:ln></p:spPr><p:style><a:lnRef idx="2"><a:schemeClr val="accent1"><a:shade val="50000"/></a:schemeClr></a:lnRef><a:fillRef idx="1"><a:schemeClr val="accent1"/></a:fillRef><a:effectRef idx="0"><a:schemeClr val="accent1"/></a:effectRef><a:fontRef idx="minor"><a:schemeClr val="lt1"/></a:fontRef></p:style><p:txBody><a:bodyPr rtlCol="0" anchor="ctr"/><a:lstStyle/><a:p><a:pPr algn="ctr"/><a:endParaRPr lang="ko-KR" altLang="en-US"/></a:p></p:txBody></p:sp><p:grpSp><p:nvGrpSpPr><p:cNvPr id="4" name="그룹 80"/><p:cNvGrpSpPr/><p:nvPr/></p:nvGrpSpPr><p:grpSpPr><a:xfrm><a:off x="102025" y="106879"/><a:ext cx="232172" cy="232172"/><a:chOff x="179512" y="38828"/><a:chExt cx="452438" cy="452438"/></a:xfrm></p:grpSpPr><p:sp><p:nvSpPr><p:cNvPr id="113" name="모서리가 둥근 직사각형 112"/><p:cNvSpPr/><p:nvPr/></p:nvSpPr><p:spPr><a:xfrm><a:off x="179512" y="38828"/><a:ext cx="452438" cy="452438"/></a:xfrm><a:prstGeom prst="roundRect"><a:avLst><a:gd name="adj" fmla="val 23281"/></a:avLst></a:prstGeom><a:solidFill><a:srgbClr val="EFEEEE"/></a:solidFill><a:ln><a:solidFill><a:srgbClr val="BEB7BD"/></a:solidFill></a:ln></p:spPr><p:style><a:lnRef idx="2"><a:schemeClr val="accent1"><a:shade val="50000"/></a:schemeClr></a:lnRef><a:fillRef idx="1"><a:schemeClr val="accent1"/></a:fillRef><a:effectRef idx="0"><a:schemeClr val="accent1"/></a:effectRef><a:fontRef idx="minor"><a:schemeClr val="lt1"/></a:fontRef></p:style><p:txBody><a:bodyPr rtlCol="0" anchor="ctr"/><a:lstStyle/><a:p><a:pPr algn="ctr"/><a:endParaRPr lang="ko-KR" altLang="en-US"/></a:p></p:txBody></p:sp><p:sp><p:nvSpPr><p:cNvPr id="114" name="이등변 삼각형 113"/><p:cNvSpPr/><p:nvPr/></p:nvSpPr><p:spPr><a:xfrm rot="16200000" flipH="1"><a:off x="236477" y="154937"/><a:ext cx="255456" cy="220220"/></a:xfrm><a:prstGeom prst="triangle"><a:avLst/></a:prstGeom><a:solidFill><a:srgbClr val="524D49"/></a:solidFill><a:ln><a:noFill/></a:ln></p:spPr><p:style><a:lnRef idx="2"><a:schemeClr val="accent1"><a:shade val="50000"/></a:schemeClr></a:lnRef><a:fillRef idx="1"><a:schemeClr val="accent1"/></a:fillRef><a:effectRef idx="0"><a:schemeClr val="accent1"/></a:effectRef><a:fontRef idx="minor"><a:schemeClr val="lt1"/></a:fontRef></p:style><p:txBody><a:bodyPr rtlCol="0" anchor="ctr"/><a:lstStyle/><a:p><a:pPr algn="ctr"/><a:endParaRPr lang="ko-KR" altLang="en-US"/></a:p></p:txBody></p:sp></p:grpSp><p:grpSp><p:nvGrpSpPr><p:cNvPr id="5" name="그룹 81"/><p:cNvGrpSpPr/><p:nvPr/></p:nvGrpSpPr><p:grpSpPr><a:xfrm><a:off x="363087" y="106879"/><a:ext cx="232172" cy="232172"/><a:chOff x="817389" y="38828"/><a:chExt cx="452438" cy="452438"/></a:xfrm></p:grpSpPr><p:sp><p:nvSpPr><p:cNvPr id="111" name="모서리가 둥근 직사각형 110"/><p:cNvSpPr/><p:nvPr/></p:nvSpPr><p:spPr><a:xfrm><a:off x="817389" y="38828"/><a:ext cx="452438" cy="452438"/></a:xfrm><a:prstGeom prst="roundRect"><a:avLst><a:gd name="adj" fmla="val 23281"/></a:avLst></a:prstGeom><a:solidFill><a:srgbClr val="EFEEEE"/></a:solidFill><a:ln><a:solidFill><a:srgbClr val="BEB7BD"/></a:solidFill></a:ln></p:spPr><p:style><a:lnRef idx="2"><a:schemeClr val="accent1"><a:shade val="50000"/></a:schemeClr></a:lnRef><a:fillRef idx="1"><a:schemeClr val="accent1"/></a:fillRef><a:effectRef idx="0"><a:schemeClr val="accent1"/></a:effectRef><a:fontRef idx="minor"><a:schemeClr val="lt1"/></a:fontRef></p:style><p:txBody><a:bodyPr rtlCol="0" anchor="ctr"/><a:lstStyle/><a:p><a:pPr algn="ctr"/><a:endParaRPr lang="ko-KR" altLang="en-US"/></a:p></p:txBody></p:sp><p:sp><p:nvSpPr><p:cNvPr id="112" name="이등변 삼각형 111"/><p:cNvSpPr/><p:nvPr/></p:nvSpPr><p:spPr><a:xfrm rot="5400000" flipH="1"><a:off x="953982" y="154937"/><a:ext cx="255456" cy="220220"/></a:xfrm><a:prstGeom prst="triangle"><a:avLst/></a:prstGeom><a:solidFill><a:srgbClr val="524D49"/></a:solidFill><a:ln><a:noFill/></a:ln></p:spPr><p:style><a:lnRef idx="2"><a:schemeClr val="accent1"><a:shade val="50000"/></a:schemeClr></a:lnRef><a:fillRef idx="1"><a:schemeClr val="accent1"/></a:fillRef><a:effectRef idx="0"><a:schemeClr val="accent1"/></a:effectRef><a:fontRef idx="minor"><a:schemeClr val="lt1"/></a:fontRef></p:style><p:txBody><a:bodyPr rtlCol="0" anchor="ctr"/><a:lstStyle/><a:p><a:pPr algn="ctr"/><a:endParaRPr lang="ko-KR" altLang="en-US"/></a:p></p:txBody></p:sp></p:grpSp><p:grpSp><p:nvGrpSpPr><p:cNvPr id="6" name="그룹 82"/><p:cNvGrpSpPr/><p:nvPr/></p:nvGrpSpPr><p:grpSpPr><a:xfrm><a:off x="632824" y="106879"/><a:ext cx="232172" cy="232172"/><a:chOff x="1403648" y="38828"/><a:chExt cx="452438" cy="452438"/></a:xfrm></p:grpSpPr><p:sp><p:nvSpPr><p:cNvPr id="109" name="모서리가 둥근 직사각형 108"/><p:cNvSpPr/><p:nvPr/></p:nvSpPr><p:spPr><a:xfrm><a:off x="1403648" y="38828"/><a:ext cx="452438" cy="452438"/></a:xfrm><a:prstGeom prst="roundRect"><a:avLst><a:gd name="adj" fmla="val 23281"/></a:avLst></a:prstGeom><a:solidFill><a:srgbClr val="EFEEEE"/></a:solidFill><a:ln><a:solidFill><a:srgbClr val="BEB7BD"/></a:solidFill></a:ln></p:spPr><p:style><a:lnRef idx="2"><a:schemeClr val="accent1"><a:shade val="50000"/></a:schemeClr></a:lnRef><a:fillRef idx="1"><a:schemeClr val="accent1"/></a:fillRef><a:effectRef idx="0"><a:schemeClr val="accent1"/></a:effectRef><a:fontRef idx="minor"><a:schemeClr val="lt1"/></a:fontRef></p:style><p:txBody><a:bodyPr rtlCol="0" anchor="ctr"/><a:lstStyle/><a:p><a:pPr algn="ctr"/><a:endParaRPr lang="ko-KR" altLang="en-US"/></a:p></p:txBody></p:sp><p:pic><p:nvPicPr><p:cNvPr id="110" name="그림 109"/><p:cNvPicPr><a:picLocks noChangeAspect="1"/></p:cNvPicPr><p:nvPr/></p:nvPicPr><p:blipFill rotWithShape="1"><a:blip r:embed="rId5" cstate="print"><a:extLst><a:ext uri="{28A0092B-C50C-407E-A947-70E740481C1C}"><a14:useLocalDpi xmlns:a14="http://schemas.microsoft.com/office/drawing/2010/main" val="0"/></a:ext></a:extLst></a:blip><a:srcRect l="6826" b="18095"/><a:stretch/></p:blipFill><p:spPr><a:xfrm rot="2966002" flipH="1" flipV="1"><a:off x="1479151" y="139123"/><a:ext cx="301432" cy="264972"/></a:xfrm><a:prstGeom prst="rect"><a:avLst/></a:prstGeom></p:spPr></p:pic></p:grpSp><p:grpSp><p:nvGrpSpPr><p:cNvPr id="7" name="그룹 83"/><p:cNvGrpSpPr/><p:nvPr/></p:nvGrpSpPr><p:grpSpPr><a:xfrm><a:off x="6222163" y="86751"/><a:ext cx="232172" cy="232172"/><a:chOff x="3893343" y="65950"/><a:chExt cx="452438" cy="452438"/></a:xfrm></p:grpSpPr><p:sp><p:nvSpPr><p:cNvPr id="107" name="모서리가 둥근 직사각형 106"/><p:cNvSpPr/><p:nvPr/></p:nvSpPr><p:spPr><a:xfrm><a:off x="3893343" y="65950"/><a:ext cx="452438" cy="452438"/></a:xfrm><a:prstGeom prst="roundRect"><a:avLst><a:gd name="adj" fmla="val 23281"/></a:avLst></a:prstGeom><a:solidFill><a:srgbClr val="EFEEEE"/></a:solidFill><a:ln><a:solidFill><a:srgbClr val="BEB7BD"/></a:solidFill></a:ln></p:spPr><p:style><a:lnRef idx="2"><a:schemeClr val="accent1"><a:shade val="50000"/></a:schemeClr></a:lnRef><a:fillRef idx="1"><a:schemeClr val="accent1"/></a:fillRef><a:effectRef idx="0"><a:schemeClr val="accent1"/></a:effectRef><a:fontRef idx="minor"><a:schemeClr val="lt1"/></a:fontRef></p:style><p:txBody><a:bodyPr rtlCol="0" anchor="ctr"/><a:lstStyle/><a:p><a:pPr algn="ctr"/><a:endParaRPr lang="ko-KR" altLang="en-US"/></a:p></p:txBody></p:sp><p:pic><p:nvPicPr><p:cNvPr id="108" name="그림 107"/><p:cNvPicPr><a:picLocks noChangeAspect="1"/></p:cNvPicPr><p:nvPr/></p:nvPicPr><p:blipFill rotWithShape="1"><a:blip r:embed="rId6" cstate="print"><a:extLst><a:ext uri="{28A0092B-C50C-407E-A947-70E740481C1C}"><a14:useLocalDpi xmlns:a14="http://schemas.microsoft.com/office/drawing/2010/main" val="0"/></a:ext></a:extLst></a:blip><a:srcRect l="4394" b="12164"/><a:stretch/></p:blipFill><p:spPr><a:xfrm><a:off x="3976687" y="160906"/><a:ext cx="285750" cy="262528"/></a:xfrm><a:prstGeom prst="rect"><a:avLst/></a:prstGeom></p:spPr></p:pic></p:grpSp><p:grpSp><p:nvGrpSpPr><p:cNvPr id="8" name="그룹 84"/><p:cNvGrpSpPr/><p:nvPr/></p:nvGrpSpPr><p:grpSpPr><a:xfrm><a:off x="1685659" y="102853"/><a:ext cx="232172" cy="232172"/><a:chOff x="4345781" y="3202781"/><a:chExt cx="452438" cy="452438"/></a:xfrm></p:grpSpPr><p:sp><p:nvSpPr><p:cNvPr id="105" name="모서리가 둥근 직사각형 104"/><p:cNvSpPr/><p:nvPr/></p:nvSpPr><p:spPr><a:xfrm><a:off x="4345781" y="3202781"/><a:ext cx="452438" cy="452438"/></a:xfrm><a:prstGeom prst="roundRect"><a:avLst><a:gd name="adj" fmla="val 23281"/></a:avLst></a:prstGeom><a:solidFill><a:srgbClr val="EFEEEE"/></a:solidFill><a:ln><a:solidFill><a:srgbClr val="BEB7BD"/></a:solidFill></a:ln></p:spPr><p:style><a:lnRef idx="2"><a:schemeClr val="accent1"><a:shade val="50000"/></a:schemeClr></a:lnRef><a:fillRef idx="1"><a:schemeClr val="accent1"/></a:fillRef><a:effectRef idx="0"><a:schemeClr val="accent1"/></a:effectRef><a:fontRef idx="minor"><a:schemeClr val="lt1"/></a:fontRef></p:style><p:txBody><a:bodyPr rtlCol="0" anchor="ctr"/><a:lstStyle/><a:p><a:pPr algn="ctr"/><a:endParaRPr lang="ko-KR" altLang="en-US"/></a:p></p:txBody></p:sp><p:pic><p:nvPicPr><p:cNvPr id="106" name="그림 105"/><p:cNvPicPr><a:picLocks noChangeAspect="1"/></p:cNvPicPr><p:nvPr/></p:nvPicPr><p:blipFill><a:blip r:embed="rId7" cstate="print"><a:extLst><a:ext uri="{28A0092B-C50C-407E-A947-70E740481C1C}"><a14:useLocalDpi xmlns:a14="http://schemas.microsoft.com/office/drawing/2010/main" val="0"/></a:ext></a:extLst></a:blip><a:stretch><a:fillRect/></a:stretch></p:blipFill><p:spPr><a:xfrm flipH="1"><a:off x="4427220" y="3284220"/><a:ext cx="289560" cy="289560"/></a:xfrm><a:prstGeom prst="rect"><a:avLst/></a:prstGeom></p:spPr></p:pic></p:grpSp><p:grpSp><p:nvGrpSpPr><p:cNvPr id="9" name="그룹 85"/><p:cNvGrpSpPr/><p:nvPr/></p:nvGrpSpPr><p:grpSpPr><a:xfrm><a:off x="939906" y="106879"/><a:ext cx="232172" cy="232172"/><a:chOff x="2560185" y="48102"/><a:chExt cx="452438" cy="452438"/></a:xfrm></p:grpSpPr><p:sp><p:nvSpPr><p:cNvPr id="103" name="모서리가 둥근 직사각형 102"/><p:cNvSpPr/><p:nvPr/></p:nvSpPr><p:spPr><a:xfrm><a:off x="2560185" y="48102"/><a:ext cx="452438" cy="452438"/></a:xfrm><a:prstGeom prst="roundRect"><a:avLst><a:gd name="adj" fmla="val 23281"/></a:avLst></a:prstGeom><a:solidFill><a:srgbClr val="EFEEEE"/></a:solidFill><a:ln><a:solidFill><a:srgbClr val="BEB7BD"/></a:solidFill></a:ln></p:spPr><p:style><a:lnRef idx="2"><a:schemeClr val="accent1"><a:shade val="50000"/></a:schemeClr></a:lnRef><a:fillRef idx="1"><a:schemeClr val="accent1"/></a:fillRef><a:effectRef idx="0"><a:schemeClr val="accent1"/></a:effectRef><a:fontRef idx="minor"><a:schemeClr val="lt1"/></a:fontRef></p:style><p:txBody><a:bodyPr rtlCol="0" anchor="ctr"/><a:lstStyle/><a:p><a:pPr algn="ctr"/><a:endParaRPr lang="ko-KR" altLang="en-US"/></a:p></p:txBody></p:sp><p:pic><p:nvPicPr><p:cNvPr id="104" name="그림 103"/><p:cNvPicPr><a:picLocks noChangeAspect="1"/></p:cNvPicPr><p:nvPr/></p:nvPicPr><p:blipFill rotWithShape="1"><a:blip r:embed="rId8" cstate="print"><a:extLst><a:ext uri="{28A0092B-C50C-407E-A947-70E740481C1C}"><a14:useLocalDpi xmlns:a14="http://schemas.microsoft.com/office/drawing/2010/main" val="0"/></a:ext></a:extLst></a:blip><a:srcRect/><a:stretch/></p:blipFill><p:spPr><a:xfrm><a:off x="2658158" y="137295"/><a:ext cx="256492" cy="255002"/></a:xfrm><a:prstGeom prst="rect"><a:avLst/></a:prstGeom></p:spPr></p:pic></p:grpSp><p:sp><p:nvSpPr><p:cNvPr id="87" name="모서리가 둥근 직사각형 86"/><p:cNvSpPr/><p:nvPr/></p:nvSpPr><p:spPr><a:xfrm><a:off x="1253611" y="106879"/><a:ext cx="232172" cy="232172"/></a:xfrm><a:prstGeom prst="roundRect"><a:avLst><a:gd name="adj" fmla="val 23281"/></a:avLst></a:prstGeom><a:solidFill><a:srgbClr val="EFEEEE"/></a:solidFill><a:ln><a:solidFill><a:srgbClr val="BEB7BD"/></a:solidFill></a:ln></p:spPr><p:style><a:lnRef idx="2"><a:schemeClr val="accent1"><a:shade val="50000"/></a:schemeClr></a:lnRef><a:fillRef idx="1"><a:schemeClr val="accent1"/></a:fillRef><a:effectRef idx="0"><a:schemeClr val="accent1"/></a:effectRef><a:fontRef idx="minor"><a:schemeClr val="lt1"/></a:fontRef></p:style><p:txBody><a:bodyPr rtlCol="0" anchor="ctr"/><a:lstStyle/><a:p><a:pPr algn="ctr"/><a:endParaRPr lang="ko-KR" altLang="en-US"/></a:p></p:txBody></p:sp><p:pic><p:nvPicPr><p:cNvPr id="88" name="그림 87"/><p:cNvPicPr><a:picLocks noChangeAspect="1"/></p:cNvPicPr><p:nvPr/></p:nvPicPr><p:blipFill rotWithShape="1"><a:blip r:embed="rId9" cstate="print"><a:extLst><a:ext uri="{28A0092B-C50C-407E-A947-70E740481C1C}"><a14:useLocalDpi xmlns:a14="http://schemas.microsoft.com/office/drawing/2010/main" val="0"/></a:ext></a:extLst></a:blip><a:srcRect/><a:stretch/></p:blipFill><p:spPr><a:xfrm><a:off x="1314954" y="169219"/><a:ext cx="109486" cy="107491"/></a:xfrm><a:prstGeom prst="rect"><a:avLst/></a:prstGeom></p:spPr></p:pic><p:grpSp><p:nvGrpSpPr><p:cNvPr id="10" name="그룹 88"/><p:cNvGrpSpPr/><p:nvPr/></p:nvGrpSpPr><p:grpSpPr><a:xfrm><a:off x="-12053" y="405866"/><a:ext cx="1162494" cy="176450"/><a:chOff x="-4762" y="404664"/><a:chExt cx="1278743" cy="194095"/></a:xfrm></p:grpSpPr><p:sp><p:nvSpPr><p:cNvPr id="101" name="모서리가 둥근 직사각형 72"/><p:cNvSpPr/><p:nvPr/></p:nvSpPr><p:spPr><a:xfrm><a:off x="-4762" y="404664"/><a:ext cx="1278743" cy="194095"/></a:xfrm><a:custGeom><a:avLst/><a:gdLst/><a:ahLst/><a:cxnLst/><a:rect l="l" t="t" r="r" b="b"/><a:pathLst><a:path w="1872208" h="258341"><a:moveTo><a:pt x="0" y="0"/></a:moveTo><a:lnTo><a:pt x="1872208" y="0"/></a:lnTo><a:lnTo><a:pt x="1872208" y="185632"/></a:lnTo><a:cubicBezTo><a:pt x="1872208" y="225788"/><a:pt x="1839655" y="258341"/><a:pt x="1799499" y="258341"/></a:cubicBezTo><a:lnTo><a:pt x="72709" y="258341"/></a:lnTo><a:cubicBezTo><a:pt x="32553" y="258341"/><a:pt x="0" y="225788"/><a:pt x="0" y="185632"/></a:cubicBezTo><a:close/></a:path></a:pathLst></a:custGeom><a:gradFill flip="none" rotWithShape="1"><a:gsLst><a:gs pos="5000"><a:schemeClr val="accent3"><a:lumMod val="75000"/></a:schemeClr></a:gs><a:gs pos="30000"><a:schemeClr val="bg1"><a:lumMod val="85000"/></a:schemeClr></a:gs></a:gsLst><a:lin ang="16200000" scaled="1"/><a:tileRect/></a:gradFill><a:ln><a:noFill/></a:ln></p:spPr><p:style><a:lnRef idx="2"><a:schemeClr val="accent1"><a:shade val="50000"/></a:schemeClr></a:lnRef><a:fillRef idx="1"><a:schemeClr val="accent1"/></a:fillRef><a:effectRef idx="0"><a:schemeClr val="accent1"/></a:effectRef><a:fontRef idx="minor"><a:schemeClr val="lt1"/></a:fontRef></p:style><p:txBody><a:bodyPr rtlCol="0" anchor="ctr"/><a:lstStyle/><a:p><a:pPr algn="ctr"/><a:endParaRPr lang="ko-KR" altLang="en-US"/></a:p></p:txBody></p:sp><p:pic><p:nvPicPr><p:cNvPr id="102" name="그림 101"/><p:cNvPicPr><a:picLocks noChangeAspect="1"/></p:cNvPicPr><p:nvPr/></p:nvPicPr><p:blipFill rotWithShape="1"><a:blip r:embed="rId10" cstate="print"><a:duotone><a:schemeClr val="bg2"><a:shade val="45000"/><a:satMod val="135000"/></a:schemeClr><a:prstClr val="white"/></a:duotone><a:extLst><a:ext uri="{28A0092B-C50C-407E-A947-70E740481C1C}"><a14:useLocalDpi xmlns:a14="http://schemas.microsoft.com/office/drawing/2010/main" val="0"/></a:ext></a:extLst></a:blip><a:srcRect/><a:stretch/></p:blipFill><p:spPr><a:xfrm><a:off x="1163087" y="501833"/><a:ext cx="82259" cy="80759"/></a:xfrm><a:prstGeom prst="rect"><a:avLst/></a:prstGeom></p:spPr></p:pic></p:grpSp><p:grpSp><p:nvGrpSpPr><p:cNvPr id="11" name="그룹 89"/><p:cNvGrpSpPr/><p:nvPr/></p:nvGrpSpPr><p:grpSpPr><a:xfrm><a:off x="1179063" y="405866"/><a:ext cx="1162494" cy="176450"/><a:chOff x="1320975" y="404664"/><a:chExt cx="1278743" cy="194095"/></a:xfrm></p:grpSpPr><p:sp><p:nvSpPr><p:cNvPr id="99" name="모서리가 둥근 직사각형 72"/><p:cNvSpPr/><p:nvPr/></p:nvSpPr><p:spPr><a:xfrm><a:off x="1320975" y="404664"/><a:ext cx="1278743" cy="194095"/></a:xfrm><a:custGeom><a:avLst/><a:gdLst/><a:ahLst/><a:cxnLst/><a:rect l="l" t="t" r="r" b="b"/><a:pathLst><a:path w="1872208" h="258341"><a:moveTo><a:pt x="0" y="0"/></a:moveTo><a:lnTo><a:pt x="1872208" y="0"/></a:lnTo><a:lnTo><a:pt x="1872208" y="185632"/></a:lnTo><a:cubicBezTo><a:pt x="1872208" y="225788"/><a:pt x="1839655" y="258341"/><a:pt x="1799499" y="258341"/></a:cubicBezTo><a:lnTo><a:pt x="72709" y="258341"/></a:lnTo><a:cubicBezTo><a:pt x="32553" y="258341"/><a:pt x="0" y="225788"/><a:pt x="0" y="185632"/></a:cubicBezTo><a:close/></a:path></a:pathLst></a:custGeom><a:gradFill flip="none" rotWithShape="1"><a:gsLst><a:gs pos="5000"><a:schemeClr val="accent3"><a:lumMod val="75000"/></a:schemeClr></a:gs><a:gs pos="30000"><a:srgbClr val="ECEDEE"/></a:gs></a:gsLst><a:lin ang="16200000" scaled="1"/><a:tileRect/></a:gradFill><a:ln><a:noFill/></a:ln></p:spPr><p:style><a:lnRef idx="2"><a:schemeClr val="accent1"><a:shade val="50000"/></a:schemeClr></a:lnRef><a:fillRef idx="1"><a:schemeClr val="accent1"/></a:fillRef><a:effectRef idx="0"><a:schemeClr val="accent1"/></a:effectRef><a:fontRef idx="minor"><a:schemeClr val="lt1"/></a:fontRef></p:style><p:txBody><a:bodyPr rtlCol="0" anchor="ctr"/><a:lstStyle/><a:p><a:pPr algn="ctr"/><a:endParaRPr lang="ko-KR" altLang="en-US"/></a:p></p:txBody></p:sp><p:pic><p:nvPicPr><p:cNvPr id="100" name="그림 99"/><p:cNvPicPr><a:picLocks noChangeAspect="1"/></p:cNvPicPr><p:nvPr/></p:nvPicPr><p:blipFill rotWithShape="1"><a:blip r:embed="rId11" cstate="print"><a:extLst><a:ext uri="{BEBA8EAE-BF5A-486C-A8C5-ECC9F3942E4B}"><a14:imgProps xmlns:a14="http://schemas.microsoft.com/office/drawing/2010/main"><a14:imgLayer r:embed="rId12"><a14:imgEffect><a14:brightnessContrast bright="100000"/></a14:imgEffect></a14:imgLayer></a14:imgProps></a:ext><a:ext uri="{28A0092B-C50C-407E-A947-70E740481C1C}"><a14:useLocalDpi xmlns:a14="http://schemas.microsoft.com/office/drawing/2010/main" val="0"/></a:ext></a:extLst></a:blip><a:srcRect/><a:stretch/></p:blipFill><p:spPr><a:xfrm><a:off x="2488824" y="501833"/><a:ext cx="82259" cy="80759"/></a:xfrm><a:prstGeom prst="rect"><a:avLst/></a:prstGeom></p:spPr></p:pic></p:grpSp><p:grpSp><p:nvGrpSpPr><p:cNvPr id="12" name="그룹 90"/><p:cNvGrpSpPr/><p:nvPr/></p:nvGrpSpPr><p:grpSpPr><a:xfrm><a:off x="2393039" y="405866"/><a:ext cx="1162494" cy="176450"/><a:chOff x="2661692" y="404664"/><a:chExt cx="1278743" cy="194095"/></a:xfrm></p:grpSpPr><p:sp><p:nvSpPr><p:cNvPr id="97" name="모서리가 둥근 직사각형 72"/><p:cNvSpPr/><p:nvPr/></p:nvSpPr><p:spPr><a:xfrm><a:off x="2661692" y="404664"/><a:ext cx="1278743" cy="194095"/></a:xfrm><a:custGeom><a:avLst/><a:gdLst/><a:ahLst/><a:cxnLst/><a:rect l="l" t="t" r="r" b="b"/><a:pathLst><a:path w="1872208" h="258341"><a:moveTo><a:pt x="0" y="0"/></a:moveTo><a:lnTo><a:pt x="1872208" y="0"/></a:lnTo><a:lnTo><a:pt x="1872208" y="185632"/></a:lnTo><a:cubicBezTo><a:pt x="1872208" y="225788"/><a:pt x="1839655" y="258341"/><a:pt x="1799499" y="258341"/></a:cubicBezTo><a:lnTo><a:pt x="72709" y="258341"/></a:lnTo><a:cubicBezTo><a:pt x="32553" y="258341"/><a:pt x="0" y="225788"/><a:pt x="0" y="185632"/></a:cubicBezTo><a:close/></a:path></a:pathLst></a:custGeom><a:gradFill flip="none" rotWithShape="1"><a:gsLst><a:gs pos="5000"><a:schemeClr val="accent3"><a:lumMod val="75000"/></a:schemeClr></a:gs><a:gs pos="30000"><a:schemeClr val="bg1"><a:lumMod val="85000"/></a:schemeClr></a:gs></a:gsLst><a:lin ang="16200000" scaled="1"/><a:tileRect/></a:gradFill><a:ln><a:noFill/></a:ln></p:spPr><p:style><a:lnRef idx="2"><a:schemeClr val="accent1"><a:shade val="50000"/></a:schemeClr></a:lnRef><a:fillRef idx="1"><a:schemeClr val="accent1"/></a:fillRef><a:effectRef idx="0"><a:schemeClr val="accent1"/></a:effectRef><a:fontRef idx="minor"><a:schemeClr val="lt1"/></a:fontRef></p:style><p:txBody><a:bodyPr rtlCol="0" anchor="ctr"/><a:lstStyle/><a:p><a:pPr algn="ctr"/><a:endParaRPr lang="ko-KR" altLang="en-US"/></a:p></p:txBody></p:sp><p:pic><p:nvPicPr><p:cNvPr id="98" name="그림 97"/><p:cNvPicPr><a:picLocks noChangeAspect="1"/></p:cNvPicPr><p:nvPr/></p:nvPicPr><p:blipFill rotWithShape="1"><a:blip r:embed="rId11" cstate="print"><a:extLst><a:ext uri="{BEBA8EAE-BF5A-486C-A8C5-ECC9F3942E4B}"><a14:imgProps xmlns:a14="http://schemas.microsoft.com/office/drawing/2010/main"><a14:imgLayer r:embed="rId12"><a14:imgEffect><a14:brightnessContrast bright="100000"/></a14:imgEffect></a14:imgLayer></a14:imgProps></a:ext><a:ext uri="{28A0092B-C50C-407E-A947-70E740481C1C}"><a14:useLocalDpi xmlns:a14="http://schemas.microsoft.com/office/drawing/2010/main" val="0"/></a:ext></a:extLst></a:blip><a:srcRect/><a:stretch/></p:blipFill><p:spPr><a:xfrm><a:off x="3829541" y="501833"/><a:ext cx="82259" cy="80759"/></a:xfrm><a:prstGeom prst="rect"><a:avLst/></a:prstGeom></p:spPr></p:pic></p:grpSp><p:grpSp><p:nvGrpSpPr><p:cNvPr id="13" name="그룹 91"/><p:cNvGrpSpPr/><p:nvPr/></p:nvGrpSpPr><p:grpSpPr><a:xfrm><a:off x="3607015" y="405866"/><a:ext cx="1162494" cy="176450"/><a:chOff x="3995936" y="404664"/><a:chExt cx="1278743" cy="194095"/></a:xfrm></p:grpSpPr><p:sp><p:nvSpPr><p:cNvPr id="95" name="모서리가 둥근 직사각형 72"/><p:cNvSpPr/><p:nvPr/></p:nvSpPr><p:spPr><a:xfrm><a:off x="3995936" y="404664"/><a:ext cx="1278743" cy="194095"/></a:xfrm><a:custGeom><a:avLst/><a:gdLst/><a:ahLst/><a:cxnLst/><a:rect l="l" t="t" r="r" b="b"/><a:pathLst><a:path w="1872208" h="258341"><a:moveTo><a:pt x="0" y="0"/></a:moveTo><a:lnTo><a:pt x="1872208" y="0"/></a:lnTo><a:lnTo><a:pt x="1872208" y="185632"/></a:lnTo><a:cubicBezTo><a:pt x="1872208" y="225788"/><a:pt x="1839655" y="258341"/><a:pt x="1799499" y="258341"/></a:cubicBezTo><a:lnTo><a:pt x="72709" y="258341"/></a:lnTo><a:cubicBezTo><a:pt x="32553" y="258341"/><a:pt x="0" y="225788"/><a:pt x="0" y="185632"/></a:cubicBezTo><a:close/></a:path></a:pathLst></a:custGeom><a:gradFill flip="none" rotWithShape="1"><a:gsLst><a:gs pos="5000"><a:schemeClr val="accent3"><a:lumMod val="75000"/></a:schemeClr></a:gs><a:gs pos="30000"><a:schemeClr val="bg1"><a:lumMod val="85000"/></a:schemeClr></a:gs></a:gsLst><a:lin ang="16200000" scaled="1"/><a:tileRect/></a:gradFill><a:ln><a:noFill/></a:ln></p:spPr><p:style><a:lnRef idx="2"><a:schemeClr val="accent1"><a:shade val="50000"/></a:schemeClr></a:lnRef><a:fillRef idx="1"><a:schemeClr val="accent1"/></a:fillRef><a:effectRef idx="0"><a:schemeClr val="accent1"/></a:effectRef><a:fontRef idx="minor"><a:schemeClr val="lt1"/></a:fontRef></p:style><p:txBody><a:bodyPr rtlCol="0" anchor="ctr"/><a:lstStyle/><a:p><a:pPr algn="ctr"/><a:endParaRPr lang="ko-KR" altLang="en-US"/></a:p></p:txBody></p:sp><p:pic><p:nvPicPr><p:cNvPr id="96" name="그림 95"/><p:cNvPicPr><a:picLocks noChangeAspect="1"/></p:cNvPicPr><p:nvPr/></p:nvPicPr><p:blipFill rotWithShape="1"><a:blip r:embed="rId11" cstate="print"><a:extLst><a:ext uri="{BEBA8EAE-BF5A-486C-A8C5-ECC9F3942E4B}"><a14:imgProps xmlns:a14="http://schemas.microsoft.com/office/drawing/2010/main"><a14:imgLayer r:embed="rId12"><a14:imgEffect><a14:brightnessContrast bright="100000"/></a14:imgEffect></a14:imgLayer></a14:imgProps></a:ext><a:ext uri="{28A0092B-C50C-407E-A947-70E740481C1C}"><a14:useLocalDpi xmlns:a14="http://schemas.microsoft.com/office/drawing/2010/main" val="0"/></a:ext></a:extLst></a:blip><a:srcRect/><a:stretch/></p:blipFill><p:spPr><a:xfrm><a:off x="5163785" y="501833"/><a:ext cx="82259" cy="80759"/></a:xfrm><a:prstGeom prst="rect"><a:avLst/></a:prstGeom></p:spPr></p:pic></p:grpSp><p:sp><p:nvSpPr><p:cNvPr id="93" name="모서리가 둥근 직사각형 92"/><p:cNvSpPr/><p:nvPr/></p:nvSpPr><p:spPr><a:xfrm rot="10800000"><a:off x="8983986" y="420117"/><a:ext cx="140348" cy="127588"/></a:xfrm><a:prstGeom prst="roundRect"><a:avLst><a:gd name="adj" fmla="val 23281"/></a:avLst></a:prstGeom><a:gradFill flip="none" rotWithShape="1"><a:gsLst><a:gs pos="0"><a:srgbClr val="CCC6C4"/></a:gs><a:gs pos="100000"><a:srgbClr val="F7F5F6"/></a:gs></a:gsLst><a:lin ang="10800000" scaled="1"/><a:tileRect/></a:gradFill><a:ln><a:noFill/></a:ln></p:spPr><p:style><a:lnRef idx="2"><a:schemeClr val="accent1"><a:shade val="50000"/></a:schemeClr></a:lnRef><a:fillRef idx="1"><a:schemeClr val="accent1"/></a:fillRef><a:effectRef idx="0"><a:schemeClr val="accent1"/></a:effectRef><a:fontRef idx="minor"><a:schemeClr val="lt1"/></a:fontRef></p:style><p:txBody><a:bodyPr rtlCol="0" anchor="ctr"/><a:lstStyle/><a:p><a:pPr algn="ctr"/><a:endParaRPr lang="ko-KR" altLang="en-US"/></a:p></p:txBody></p:sp><p:sp><p:nvSpPr><p:cNvPr id="94" name="이등변 삼각형 93"/><p:cNvSpPr/><p:nvPr/></p:nvSpPr><p:spPr><a:xfrm flipH="1"><a:off x="9017589" y="444353"/><a:ext cx="73140" cy="63052"/></a:xfrm><a:prstGeom prst="triangle"><a:avLst/></a:prstGeom><a:solidFill><a:srgbClr val="524D49"/></a:solidFill><a:ln><a:noFill/></a:ln></p:spPr><p:style><a:lnRef idx="2"><a:schemeClr val="accent1"><a:shade val="50000"/></a:schemeClr></a:lnRef><a:fillRef idx="1"><a:schemeClr val="accent1"/></a:fillRef><a:effectRef idx="0"><a:schemeClr val="accent1"/></a:effectRef><a:fontRef idx="minor"><a:schemeClr val="lt1"/></a:fontRef></p:style><p:txBody><a:bodyPr rtlCol="0" anchor="ctr"/><a:lstStyle/><a:p><a:pPr algn="ctr"/><a:endParaRPr lang="ko-KR" altLang="en-US"/></a:p></p:txBody></p:sp></p:grpSp><p:grpSp><p:nvGrpSpPr><p:cNvPr id="14" name="그룹 63"/><p:cNvGrpSpPr/><p:nvPr/></p:nvGrpSpPr><p:grpSpPr><a:xfrm><a:off x="10528755" y="4543800"/><a:ext cx="110855" cy="757409"/><a:chOff x="9004754" y="579160"/><a:chExt cx="110855" cy="757409"/></a:xfrm></p:grpSpPr><p:sp><p:nvSpPr><p:cNvPr id="65" name="모서리가 둥근 직사각형 64"/><p:cNvSpPr/><p:nvPr/></p:nvSpPr><p:spPr><a:xfrm rot="10800000"><a:off x="9004754" y="579160"/><a:ext cx="110855" cy="757409"/></a:xfrm><a:prstGeom prst="roundRect"><a:avLst/></a:prstGeom><a:gradFill><a:gsLst><a:gs pos="0"><a:srgbClr val="CCC6C4"/></a:gs><a:gs pos="100000"><a:srgbClr val="F7F5F6"/></a:gs></a:gsLst><a:lin ang="10800000" scaled="1"/></a:gradFill><a:ln><a:noFill/></a:ln></p:spPr><p:style><a:lnRef idx="2"><a:schemeClr val="accent1"><a:shade val="50000"/></a:schemeClr></a:lnRef><a:fillRef idx="1"><a:schemeClr val="accent1"/></a:fillRef><a:effectRef idx="0"><a:schemeClr val="accent1"/></a:effectRef><a:fontRef idx="minor"><a:schemeClr val="lt1"/></a:fontRef></p:style><p:txBody><a:bodyPr rtlCol="0" anchor="ctr"/><a:lstStyle/><a:p><a:pPr algn="ctr"/><a:endParaRPr lang="ko-KR" altLang="en-US"/></a:p></p:txBody></p:sp><p:sp><p:nvSpPr><p:cNvPr id="66" name="모서리가 둥근 직사각형 65"/><p:cNvSpPr/><p:nvPr/></p:nvSpPr><p:spPr><a:xfrm><a:off x="9017617" y="918339"/><a:ext cx="91775" cy="15672"/></a:xfrm><a:prstGeom prst="roundRect"><a:avLst><a:gd name="adj" fmla="val 50000"/></a:avLst></a:prstGeom><a:solidFill><a:srgbClr val="524D49"/></a:solidFill><a:ln><a:noFill/></a:ln></p:spPr><p:style><a:lnRef idx="2"><a:schemeClr val="accent1"><a:shade val="50000"/></a:schemeClr></a:lnRef><a:fillRef idx="1"><a:schemeClr val="accent1"/></a:fillRef><a:effectRef idx="0"><a:schemeClr val="accent1"/></a:effectRef><a:fontRef idx="minor"><a:schemeClr val="lt1"/></a:fontRef></p:style><p:txBody><a:bodyPr rtlCol="0" anchor="ctr"/><a:lstStyle/><a:p><a:pPr algn="ctr"/><a:endParaRPr lang="ko-KR" altLang="en-US"/></a:p></p:txBody></p:sp><p:sp><p:nvSpPr><p:cNvPr id="67" name="모서리가 둥근 직사각형 66"/><p:cNvSpPr/><p:nvPr/></p:nvSpPr><p:spPr><a:xfrm><a:off x="9017617" y="988661"/><a:ext cx="91775" cy="17239"/></a:xfrm><a:prstGeom prst="roundRect"><a:avLst><a:gd name="adj" fmla="val 50000"/></a:avLst></a:prstGeom><a:solidFill><a:srgbClr val="524D49"/></a:solidFill><a:ln><a:noFill/></a:ln></p:spPr><p:style><a:lnRef idx="2"><a:schemeClr val="accent1"><a:shade val="50000"/></a:schemeClr></a:lnRef><a:fillRef idx="1"><a:schemeClr val="accent1"/></a:fillRef><a:effectRef idx="0"><a:schemeClr val="accent1"/></a:effectRef><a:fontRef idx="minor"><a:schemeClr val="lt1"/></a:fontRef></p:style><p:txBody><a:bodyPr rtlCol="0" anchor="ctr"/><a:lstStyle/><a:p><a:pPr algn="ctr"/><a:endParaRPr lang="ko-KR" altLang="en-US"/></a:p></p:txBody></p:sp><p:sp><p:nvSpPr><p:cNvPr id="68" name="모서리가 둥근 직사각형 67"/><p:cNvSpPr/><p:nvPr/></p:nvSpPr><p:spPr><a:xfrm><a:off x="9017617" y="846619"/><a:ext cx="91775" cy="16899"/></a:xfrm><a:prstGeom prst="roundRect"><a:avLst><a:gd name="adj" fmla="val 50000"/></a:avLst></a:prstGeom><a:solidFill><a:srgbClr val="524D49"/></a:solidFill><a:ln><a:noFill/></a:ln></p:spPr><p:style><a:lnRef idx="2"><a:schemeClr val="accent1"><a:shade val="50000"/></a:schemeClr></a:lnRef><a:fillRef idx="1"><a:schemeClr val="accent1"/></a:fillRef><a:effectRef idx="0"><a:schemeClr val="accent1"/></a:effectRef><a:fontRef idx="minor"><a:schemeClr val="lt1"/></a:fontRef></p:style><p:txBody><a:bodyPr rtlCol="0" anchor="ctr"/><a:lstStyle/><a:p><a:pPr algn="ctr"/><a:endParaRPr lang="ko-KR" altLang="en-US"/></a:p></p:txBody></p:sp></p:grpSp><p:sp><p:nvSpPr><p:cNvPr id="70" name="타원 69"/><p:cNvSpPr/><p:nvPr/></p:nvSpPr><p:spPr><a:xfrm><a:off x="9575244" y="6445457"/><a:ext cx="360040" cy="385192"/></a:xfrm><a:prstGeom prst="ellipse"><a:avLst/></a:prstGeom><a:solidFill><a:schemeClr val="bg1"><a:lumMod val="50000"/><a:alpha val="60000"/></a:schemeClr></a:solidFill><a:ln><a:noFill/></a:ln></p:spPr><p:style><a:lnRef idx="2"><a:schemeClr val="accent1"><a:shade val="50000"/></a:schemeClr></a:lnRef><a:fillRef idx="1"><a:schemeClr val="accent1"/></a:fillRef><a:effectRef idx="0"><a:schemeClr val="accent1"/></a:effectRef><a:fontRef idx="minor"><a:schemeClr val="lt1"/></a:fontRef></p:style><p:txBody><a:bodyPr rtlCol="0" anchor="ctr"/><a:lstStyle/><a:p><a:pPr algn="ctr"/><a:endParaRPr lang="ko-KR" altLang="en-US" sz="1600" dirty="0"><a:solidFill><a:schemeClr val="tx1"><a:lumMod val="50000"/><a:lumOff val="50000"/></a:schemeClr></a:solidFill></a:endParaRPr></a:p></p:txBody></p:sp><p:sp><p:nvSpPr><p:cNvPr id="116" name="TextBox 115"/><p:cNvSpPr txBox="1"/><p:nvPr/></p:nvSpPr><p:spPr><a:xfrm><a:off x="4252952" y="64063"/><a:ext cx="3211201" cy="276999"/></a:xfrm><a:prstGeom prst="rect"><a:avLst/></a:prstGeom><a:noFill/></p:spPr><p:txBody><a:bodyPr wrap="square" rtlCol="0"><a:spAutoFit/></a:bodyPr><a:lstStyle/><a:p><a:r><a:rPr lang="en-US" altLang="ko-KR" sz="1200" dirty="0"><a:ln><a:solidFill><a:schemeClr val="tx1"><a:alpha val="20000"/></a:schemeClr></a:solidFill></a:ln><a:latin typeface="a고딕15" pitchFamily="18" charset="-127"/><a:ea typeface="a고딕15" pitchFamily="18" charset="-127"/></a:rPr><a:t>http://cafe.naver.com/</a:t></a:r><a:r><a:rPr lang="ko-KR" altLang="en-US" sz="1200" dirty="0"><a:ln><a:solidFill><a:schemeClr val="tx1"><a:alpha val="20000"/></a:schemeClr></a:solidFill></a:ln><a:latin typeface="a고딕15" pitchFamily="18" charset="-127"/><a:ea typeface="a고딕15" pitchFamily="18" charset="-127"/></a:rPr><a:t>폭력과문화</a:t></a:r><a:endParaRPr lang="en-US" altLang="ko-KR" sz="1200" dirty="0"><a:ln><a:solidFill><a:schemeClr val="tx1"><a:alpha val="20000"/></a:schemeClr></a:solidFill></a:ln><a:latin typeface="a고딕15" pitchFamily="18" charset="-127"/><a:ea typeface="a고딕15" pitchFamily="18" charset="-127"/></a:endParaRPr></a:p></p:txBody></p:sp><p:sp><p:nvSpPr><p:cNvPr id="117" name="TextBox 116"/><p:cNvSpPr txBox="1"/><p:nvPr/></p:nvSpPr><p:spPr><a:xfrm><a:off x="7968208" y="64063"/><a:ext cx="2088232" cy="276999"/></a:xfrm><a:prstGeom prst="rect"><a:avLst/></a:prstGeom><a:noFill/></p:spPr><p:txBody><a:bodyPr wrap="square" rtlCol="0"><a:spAutoFit/></a:bodyPr><a:lstStyle/><a:p><a:r><a:rPr lang="ko-KR" altLang="en-US" sz="1200" dirty="0"><a:ln><a:solidFill><a:schemeClr val="tx1"><a:alpha val="20000"/></a:schemeClr></a:solidFill></a:ln><a:latin typeface="a고딕15" pitchFamily="18" charset="-127"/><a:ea typeface="a고딕15" pitchFamily="18" charset="-127"/></a:rPr><a:t>동양인 인종차별 사례</a:t></a:r></a:p></p:txBody></p:sp><p:sp><p:nvSpPr><p:cNvPr id="118" name="TextBox 117"/><p:cNvSpPr txBox="1"/><p:nvPr/></p:nvSpPr><p:spPr><a:xfrm><a:off x="8832304" y="6427113"/><a:ext cx="3312368" cy="261610"/></a:xfrm><a:prstGeom prst="rect"><a:avLst/></a:prstGeom><a:noFill/></p:spPr><p:txBody><a:bodyPr wrap="square" rtlCol="0"><a:spAutoFit/></a:bodyPr><a:lstStyle/><a:p><a:pPr algn="just"/><a:endParaRPr lang="en-US" altLang="ko-KR" sz="1100" dirty="0"><a:solidFill><a:schemeClr val="tx1"><a:lumMod val="75000"/><a:lumOff val="25000"/></a:schemeClr></a:solidFill><a:latin typeface="a카툰" pitchFamily="18" charset="-127"/><a:ea typeface="a카툰" pitchFamily="18" charset="-127"/></a:endParaRPr></a:p></p:txBody></p:sp><p:sp><p:nvSpPr><p:cNvPr id="69" name="TextBox 68"/><p:cNvSpPr txBox="1"/><p:nvPr/></p:nvSpPr><p:spPr><a:xfrm><a:off x="2495601" y="2492897"/><a:ext cx="4190571" cy="800219"/></a:xfrm><a:prstGeom prst="rect"><a:avLst/></a:prstGeom><a:noFill/></p:spPr><p:txBody><a:bodyPr wrap="none" rtlCol="0"><a:spAutoFit/></a:bodyPr><a:lstStyle/><a:p><a:r><a:rPr lang="en-US" altLang="ko-KR" dirty="0" err="1"><a:latin typeface="a고딕15" pitchFamily="18" charset="-127"/><a:ea typeface="a고딕15" pitchFamily="18" charset="-127"/><a:cs typeface="함초롬돋움" pitchFamily="50" charset="-127"/></a:rPr><a:t>Ching</a:t></a:r><a:r><a:rPr lang="en-US" altLang="ko-KR" dirty="0"><a:latin typeface="a고딕15" pitchFamily="18" charset="-127"/><a:ea typeface="a고딕15" pitchFamily="18" charset="-127"/><a:cs typeface="함초롬돋움" pitchFamily="50" charset="-127"/></a:rPr><a:t> Chong</a:t></a:r></a:p><a:p><a:r><a:rPr lang="ko-KR" altLang="en-US" sz="1400" dirty="0"><a:latin typeface="a고딕15" pitchFamily="18" charset="-127"/><a:ea typeface="a고딕15" pitchFamily="18" charset="-127"/><a:cs typeface="함초롬돋움" pitchFamily="50" charset="-127"/></a:rPr><a:t>중국인의 억양을 희화화한 단어</a:t></a:r><a:r><a:rPr lang="en-US" altLang="ko-KR" sz="1400" dirty="0"><a:latin typeface="a고딕15" pitchFamily="18" charset="-127"/><a:ea typeface="a고딕15" pitchFamily="18" charset="-127"/><a:cs typeface="함초롬돋움" pitchFamily="50" charset="-127"/></a:rPr><a:t>. </a:t></a:r><a:r><a:rPr lang="ko-KR" altLang="en-US" sz="1400" dirty="0"><a:latin typeface="a고딕15" pitchFamily="18" charset="-127"/><a:ea typeface="a고딕15" pitchFamily="18" charset="-127"/><a:cs typeface="함초롬돋움" pitchFamily="50" charset="-127"/></a:rPr><a:t>중국인 뿐 아니라</a:t></a:r><a:endParaRPr lang="en-US" altLang="ko-KR" sz="1400" dirty="0"><a:latin typeface="a고딕15" pitchFamily="18" charset="-127"/><a:ea typeface="a고딕15" pitchFamily="18" charset="-127"/><a:cs typeface="함초롬돋움" pitchFamily="50" charset="-127"/></a:endParaRPr></a:p><a:p><a:r><a:rPr lang="ko-KR" altLang="en-US" sz="1400" dirty="0"><a:latin typeface="a고딕15" pitchFamily="18" charset="-127"/><a:ea typeface="a고딕15" pitchFamily="18" charset="-127"/><a:cs typeface="함초롬돋움" pitchFamily="50" charset="-127"/></a:rPr><a:t>일본인</a:t></a:r><a:r><a:rPr lang="en-US" altLang="ko-KR" sz="1400" dirty="0"><a:latin typeface="a고딕15" pitchFamily="18" charset="-127"/><a:ea typeface="a고딕15" pitchFamily="18" charset="-127"/><a:cs typeface="함초롬돋움" pitchFamily="50" charset="-127"/></a:rPr><a:t>, </a:t></a:r><a:r><a:rPr lang="ko-KR" altLang="en-US" sz="1400" dirty="0"><a:latin typeface="a고딕15" pitchFamily="18" charset="-127"/><a:ea typeface="a고딕15" pitchFamily="18" charset="-127"/><a:cs typeface="함초롬돋움" pitchFamily="50" charset="-127"/></a:rPr><a:t>한국인에게도 다르지 않음</a:t></a:r><a:r><a:rPr lang="en-US" altLang="ko-KR" sz="1400" dirty="0"><a:latin typeface="함초롬돋움" pitchFamily="50" charset="-127"/><a:ea typeface="함초롬돋움" pitchFamily="50" charset="-127"/><a:cs typeface="함초롬돋움" pitchFamily="50" charset="-127"/></a:rPr><a:t> </a:t></a:r><a:endParaRPr lang="ko-KR" altLang="en-US" sz="1400" dirty="0"><a:latin typeface="함초롬돋움" pitchFamily="50" charset="-127"/><a:ea typeface="함초롬돋움" pitchFamily="50" charset="-127"/><a:cs typeface="함초롬돋움" pitchFamily="50" charset="-127"/></a:endParaRPr></a:p></p:txBody></p:sp><p:sp><p:nvSpPr><p:cNvPr id="73" name="TextBox 72"/><p:cNvSpPr txBox="1"/><p:nvPr/></p:nvSpPr><p:spPr><a:xfrm><a:off x="2893698" y="3743717"/><a:ext cx="3967753" cy="400110"/></a:xfrm><a:prstGeom prst="rect"><a:avLst/></a:prstGeom><a:noFill/></p:spPr><p:txBody><a:bodyPr wrap="none" rtlCol="0"><a:spAutoFit/></a:bodyPr><a:lstStyle/><a:p><a:r><a:rPr lang="ko-KR" altLang="en-US" sz="2000" b="1" dirty="0"><a:latin typeface="a고딕15" pitchFamily="18" charset="-127"/><a:ea typeface="a고딕15" pitchFamily="18" charset="-127"/><a:cs typeface="함초롬돋움" pitchFamily="50" charset="-127"/></a:rPr><a:t>영화에서 볼 수 있는 동양인 비하</a:t></a:r></a:p></p:txBody></p:sp><p:sp><p:nvSpPr><p:cNvPr id="75" name="TextBox 74"/><p:cNvSpPr txBox="1"/><p:nvPr/></p:nvSpPr><p:spPr><a:xfrm><a:off x="2564658" y="4592587"/><a:ext cx="1136850" cy="369332"/></a:xfrm><a:prstGeom prst="rect"><a:avLst/></a:prstGeom><a:noFill/></p:spPr><p:txBody><a:bodyPr wrap="none" rtlCol="0"><a:spAutoFit/></a:bodyPr><a:lstStyle/><a:p><a:r><a:rPr lang="en-US" altLang="ko-KR" dirty="0"><a:latin typeface="a고딕15" pitchFamily="18" charset="-127"/><a:ea typeface="a고딕15" pitchFamily="18" charset="-127"/><a:cs typeface="함초롬돋움" pitchFamily="50" charset="-127"/></a:rPr><a:t>1. </a:t></a:r><a:r><a:rPr lang="ko-KR" altLang="en-US" dirty="0" err="1"><a:latin typeface="a고딕15" pitchFamily="18" charset="-127"/><a:ea typeface="a고딕15" pitchFamily="18" charset="-127"/><a:cs typeface="함초롬돋움" pitchFamily="50" charset="-127"/></a:rPr><a:t>버드맨</a:t></a:r><a:endParaRPr lang="ko-KR" altLang="en-US" dirty="0"><a:latin typeface="a고딕15" pitchFamily="18" charset="-127"/><a:ea typeface="a고딕15" pitchFamily="18" charset="-127"/><a:cs typeface="함초롬돋움" pitchFamily="50" charset="-127"/></a:endParaRPr></a:p></p:txBody></p:sp><p:pic><p:nvPicPr><p:cNvPr id="76" name="그림 75"/><p:cNvPicPr><a:picLocks noChangeAspect="1"/></p:cNvPicPr><p:nvPr/></p:nvPicPr><p:blipFill><a:blip r:embed="rId13" cstate="print"><a:extLst><a:ext uri="{28A0092B-C50C-407E-A947-70E740481C1C}"><a14:useLocalDpi xmlns:a14="http://schemas.microsoft.com/office/drawing/2010/main" val="0"/></a:ext></a:extLst></a:blip><a:stretch><a:fillRect/></a:stretch></p:blipFill><p:spPr><a:xfrm><a:off x="2685645" y="5464262"/><a:ext cx="864096" cy="981308"/></a:xfrm><a:prstGeom prst="rect"><a:avLst/></a:prstGeom></p:spPr></p:pic><p:sp><p:nvSpPr><p:cNvPr id="119" name="타원형 설명선 118"/><p:cNvSpPr/><p:nvPr/></p:nvSpPr><p:spPr><a:xfrm><a:off x="3354468" y="5022894"/><a:ext cx="1368152" cy="432048"/></a:xfrm><a:prstGeom prst="wedgeEllipseCallout"><a:avLst/></a:prstGeom><a:solidFill><a:schemeClr val="tx2"><a:lumMod val="75000"/></a:schemeClr></a:solidFill><a:ln><a:noFill/></a:ln></p:spPr><p:style><a:lnRef idx="2"><a:schemeClr val="accent1"><a:shade val="50000"/></a:schemeClr></a:lnRef><a:fillRef idx="1"><a:schemeClr val="accent1"/></a:fillRef><a:effectRef idx="0"><a:schemeClr val="accent1"/></a:effectRef><a:fontRef idx="minor"><a:schemeClr val="lt1"/></a:fontRef></p:style><p:txBody><a:bodyPr rtlCol="0" anchor="ctr"/><a:lstStyle/><a:p><a:pPr algn="ctr"/><a:r><a:rPr lang="en-US" altLang="ko-KR" sz="1050" dirty="0"><a:latin typeface="a고딕15" pitchFamily="18" charset="-127"/><a:ea typeface="a고딕15" pitchFamily="18" charset="-127"/></a:rPr><a:t>'X</a:t></a:r><a:r><a:rPr lang="ko-KR" altLang="en-US" sz="1050" dirty="0"><a:latin typeface="a고딕15" pitchFamily="18" charset="-127"/><a:ea typeface="a고딕15" pitchFamily="18" charset="-127"/></a:rPr><a:t>같은 김치 냄새가 난다</a:t></a:r><a:r><a:rPr lang="en-US" altLang="ko-KR" sz="1050" dirty="0"><a:latin typeface="HY견고딕" pitchFamily="18" charset="-127"/><a:ea typeface="HY견고딕" pitchFamily="18" charset="-127"/></a:rPr><a:t>'</a:t></a:r><a:endParaRPr lang="ko-KR" altLang="en-US" sz="1050" dirty="0"><a:latin typeface="HY견고딕" pitchFamily="18" charset="-127"/><a:ea typeface="HY견고딕" pitchFamily="18" charset="-127"/></a:endParaRPr></a:p></p:txBody></p:sp><p:pic><p:nvPicPr><p:cNvPr id="120" name="그림 119" descr="mug_obj_20150421115724433.jpg"/><p:cNvPicPr><a:picLocks noChangeAspect="1"/></p:cNvPicPr><p:nvPr/></p:nvPicPr><p:blipFill><a:blip r:embed="rId14" cstate="print"/><a:stretch><a:fillRect/></a:stretch></p:blipFill><p:spPr><a:xfrm><a:off x="7032104" y="1262636"/><a:ext cx="2377440" cy="3474720"/></a:xfrm><a:prstGeom prst="rect"><a:avLst/></a:prstGeom></p:spPr></p:pic><p:sp><p:nvSpPr><p:cNvPr id="121" name="TextBox 120"/><p:cNvSpPr txBox="1"/><p:nvPr/></p:nvSpPr><p:spPr><a:xfrm><a:off x="4655841" y="4581129"/><a:ext cx="1978427" cy="646331"/></a:xfrm><a:prstGeom prst="rect"><a:avLst/></a:prstGeom><a:noFill/></p:spPr><p:txBody><a:bodyPr wrap="none" rtlCol="0"><a:spAutoFit/></a:bodyPr><a:lstStyle/><a:p><a:r><a:rPr lang="en-US" altLang="ko-KR" dirty="0"><a:latin typeface="a고딕15" pitchFamily="18" charset="-127"/><a:ea typeface="a고딕15" pitchFamily="18" charset="-127"/><a:cs typeface="함초롬돋움" pitchFamily="50" charset="-127"/></a:rPr><a:t>2. 007</a:t></a:r><a:r><a:rPr lang="ko-KR" altLang="en-US" dirty="0" err="1"><a:latin typeface="a고딕15" pitchFamily="18" charset="-127"/><a:ea typeface="a고딕15" pitchFamily="18" charset="-127"/><a:cs typeface="함초롬돋움" pitchFamily="50" charset="-127"/></a:rPr><a:t>어나더데이</a:t></a:r><a:endParaRPr lang="en-US" altLang="ko-KR" dirty="0"><a:latin typeface="a고딕15" pitchFamily="18" charset="-127"/><a:ea typeface="a고딕15" pitchFamily="18" charset="-127"/><a:cs typeface="함초롬돋움" pitchFamily="50" charset="-127"/></a:endParaRPr></a:p><a:p><a:r><a:rPr lang="ko-KR" altLang="en-US" dirty="0"><a:latin typeface="a고딕15" pitchFamily="18" charset="-127"/><a:ea typeface="a고딕15" pitchFamily="18" charset="-127"/><a:cs typeface="함초롬돋움" pitchFamily="50" charset="-127"/></a:rPr><a:t>   북한 비하</a:t></a:r></a:p></p:txBody></p:sp><p:pic><p:nvPicPr><p:cNvPr id="122" name="그림 121" descr="(007%BE%B4%F5%B5%A5%C0%CC)James.Bond.-.Die.Another.Day_By.Ripperbanden.CD2.avi.jpg"/><p:cNvPicPr><a:picLocks noChangeAspect="1"/></p:cNvPicPr><p:nvPr/></p:nvPicPr><p:blipFill><a:blip r:embed="rId15" cstate="print"/><a:stretch><a:fillRect/></a:stretch></p:blipFill><p:spPr><a:xfrm><a:off x="7544730" y="2363583"/><a:ext cx="2448272" cy="3490685"/></a:xfrm><a:prstGeom prst="rect"><a:avLst/></a:prstGeom></p:spPr></p:pic><p:pic><p:nvPicPr><p:cNvPr id="2050" name="Picture 2" descr="C:\Users\ky766\AppData\Local\Microsoft\Windows\INetCache\IE\W173VK2T\팝콘[1].jpg"/><p:cNvPicPr><a:picLocks noChangeAspect="1" noChangeArrowheads="1"/></p:cNvPicPr><p:nvPr/></p:nvPicPr><p:blipFill><a:blip r:embed="rId16" cstate="print"/><a:srcRect/><a:stretch><a:fillRect/></a:stretch></p:blipFill><p:spPr bwMode="auto"><a:xfrm><a:off x="1909873" y="3604684"/><a:ext cx="886853" cy="792088"/></a:xfrm><a:prstGeom prst="rect"><a:avLst/></a:prstGeom><a:noFill/></p:spPr></p:pic><p:sp><p:nvSpPr><p:cNvPr id="2" name="TextBox 1"/><p:cNvSpPr txBox="1"/><p:nvPr/></p:nvSpPr><p:spPr><a:xfrm><a:off x="2906275" y="1496057"/><a:ext cx="2995075" cy="400110"/></a:xfrm><a:prstGeom prst="rect"><a:avLst/></a:prstGeom><a:noFill/></p:spPr><p:txBody><a:bodyPr wrap="square" rtlCol="0"><a:spAutoFit/></a:bodyPr><a:lstStyle/><a:p><a:pPr algn="ctr"/><a:r><a:rPr lang="ko-KR" altLang="en-US" sz="2000" b="1" dirty="0"><a:latin typeface="a고딕15" pitchFamily="18" charset="-127"/><a:ea typeface="a고딕15" pitchFamily="18" charset="-127"/><a:cs typeface="함초롬돋움" pitchFamily="50" charset="-127"/></a:rPr><a:t>언어적 인종차별 사례</a:t></a:r></a:p></p:txBody></p:sp><p:sp><p:nvSpPr><p:cNvPr id="115" name="직사각형 114"/><p:cNvSpPr/><p:nvPr/></p:nvSpPr><p:spPr><a:xfrm><a:off x="3020359" y="4166231"/><a:ext cx="3478505" cy="45719"/></a:xfrm><a:prstGeom prst="rect"><a:avLst/></a:prstGeom><a:solidFill><a:srgbClr val="FFFF00"/></a:solidFill><a:ln><a:noFill/></a:ln></p:spPr><p:style><a:lnRef idx="2"><a:schemeClr val="accent1"><a:shade val="50000"/></a:schemeClr></a:lnRef><a:fillRef idx="1"><a:schemeClr val="accent1"/></a:fillRef><a:effectRef idx="0"><a:schemeClr val="accent1"/></a:effectRef><a:fontRef idx="minor"><a:schemeClr val="lt1"/></a:fontRef></p:style><p:txBody><a:bodyPr rtlCol="0" anchor="ctr"/><a:lstStyle/><a:p><a:pPr algn="ctr"/><a:endParaRPr lang="ko-KR" altLang="en-US"/></a:p></p:txBody></p:sp></p:spTree><p:extLst><p:ext uri="{BB962C8B-B14F-4D97-AF65-F5344CB8AC3E}"><p14:creationId xmlns:p14="http://schemas.microsoft.com/office/powerpoint/2010/main" val="119228944"/></p:ext></p:extLst></p:cSld><p:clrMapOvr><a:masterClrMapping/></p:clrMapOvr><mc:AlternateContent xmlns:mc="http://schemas.openxmlformats.org/markup-compatibility/2006" xmlns:p14="http://schemas.microsoft.com/office/powerpoint/2010/main"><mc:Choice Requires="p14"><p:transition spd="med" p14:dur="700"><p:fade/></p:transition></mc:Choice><mc:Fallback xmlns=""><p:transition spd="med"><p:fade/></p:transition></mc:Fallback></mc:AlternateContent><p:timing><p:tnLst><p:par><p:cTn id="1" dur="indefinite" restart="never" nodeType="tmRoot"><p:childTnLst><p:seq concurrent="1" nextAc="seek"><p:cTn id="2" dur="indefinite" nodeType="mainSeq"><p:childTnLst><p:par><p:cTn id="3" fill="hold"><p:stCondLst><p:cond delay="indefinite"/><p:cond evt="onBegin" delay="0"><p:tn val="2"/></p:cond></p:stCondLst><p:childTnLst><p:par><p:cTn id="4" fill="hold"><p:stCondLst><p:cond delay="0"/></p:stCondLst><p:childTnLst><p:par><p:cTn id="5" presetID="10" presetClass="entr" presetSubtype="0" fill="hold" nodeType="withEffect"><p:stCondLst><p:cond delay="0"/></p:stCondLst><p:childTnLst><p:set><p:cBhvr><p:cTn id="6" dur="1" fill="hold"><p:stCondLst><p:cond delay="0"/></p:stCondLst></p:cTn><p:tgtEl><p:spTgt spid="10243"/></p:tgtEl><p:attrNameLst><p:attrName>style.visibility</p:attrName></p:attrNameLst></p:cBhvr><p:to><p:strVal val="visible"/></p:to></p:set><p:animEffect transition="in" filter="fade"><p:cBhvr><p:cTn id="7" dur="500"/><p:tgtEl><p:spTgt spid="10243"/></p:tgtEl></p:cBhvr></p:animEffect></p:childTnLst></p:cTn></p:par><p:par><p:cTn id="8" presetID="22" presetClass="entr" presetSubtype="4" fill="hold" grpId="0" nodeType="withEffect" nodePh="1"><p:stCondLst><p:cond delay="200"/></p:stCondLst><p:endCondLst><p:cond evt="begin" delay="0"><p:tn val="8"/></p:cond></p:endCondLst><p:childTnLst><p:set><p:cBhvr><p:cTn id="9" dur="1" fill="hold"><p:stCondLst><p:cond delay="0"/></p:stCondLst></p:cTn><p:tgtEl><p:spTgt spid="51"/></p:tgtEl><p:attrNameLst><p:attrName>style.visibility</p:attrName></p:attrNameLst></p:cBhvr><p:to><p:strVal val="visible"/></p:to></p:set><p:animEffect transition="in" filter="wipe(down)"><p:cBhvr><p:cTn id="10" dur="500"/><p:tgtEl><p:spTgt spid="51"/></p:tgtEl></p:cBhvr></p:animEffect></p:childTnLst></p:cTn></p:par><p:par><p:cTn id="11" presetID="22" presetClass="entr" presetSubtype="4" fill="hold" grpId="0" nodeType="withEffect" nodePh="1"><p:stCondLst><p:cond delay="200"/></p:stCondLst><p:endCondLst><p:cond evt="begin" delay="0"><p:tn val="11"/></p:cond></p:endCondLst><p:childTnLst><p:set><p:cBhvr><p:cTn id="12" dur="1" fill="hold"><p:stCondLst><p:cond delay="0"/></p:stCondLst></p:cTn><p:tgtEl><p:spTgt spid="52"/></p:tgtEl><p:attrNameLst><p:attrName>style.visibility</p:attrName></p:attrNameLst></p:cBhvr><p:to><p:strVal val="visible"/></p:to></p:set><p:animEffect transition="in" filter="wipe(down)"><p:cBhvr><p:cTn id="13" dur="500"/><p:tgtEl><p:spTgt spid="52"/></p:tgtEl></p:cBhvr></p:animEffect></p:childTnLst></p:cTn></p:par></p:childTnLst></p:cTn></p:par></p:childTnLst></p:cTn></p:par></p:childTnLst></p:cTn><p:prevCondLst><p:cond evt="onPrev" delay="0"><p:tgtEl><p:sldTgt/></p:tgtEl></p:cond></p:prevCondLst><p:nextCondLst><p:cond evt="onNext" delay="0"><p:tgtEl><p:sldTgt/></p:tgtEl></p:cond></p:nextCondLst></p:seq></p:childTnLst></p:cTn></p:par></p:tnLst><p:bldLst><p:bldP spid="51" grpId="0"/><p:bldP spid="52" grpId="0"/></p:bldLst></p:timing></p:sld>